{"player.png": [123, 74, 62], "player_back.png": [114, 68, 56], "mcl_skins_player_dummy.png": [125, 125, 125], "mcl_skins_player_1.png": [103, 100, 86], "mcl_skins_button.png": [121, 95, 85], "mcl_skins_character_1.png": [93, 90, 77], "mcl_hunger_bar_saturation.png": [255, 255, 0], "hbhunger_bar_health_poison.png": [148, 120, 24], "mcl_hunger_bar_exhaustion.png": [255, 255, 255], "mcl_hunger_icon_exhaustion.png": [213, 213, 213], "mcl_hunger_bgicon_exhaustion.png": [25, 25, 26], "mcl_hunger_icon_foodpoison.png": [109, 106, 40], "mcl_hunger_bgicon_saturation.png": [24, 24, 26], "hbhunger_bar.png": [200, 103, 0], "hbhunger_bgicon.png": [24, 24, 26], "hbhunger_icon_health_poison.png": [69, 98, 45], "mcl_hunger_bar_foodpoison.png": [116, 132, 88], "hbhunger_icon.png": [175, 132, 97], "mcl_hunger_icon_saturation.png": [157, 140, 64], "mcl_playerplus_end_sky.png": [14, 14, 14], "mobs_mc_llama_decor_purple.png": [98, 50, 98], "mobs_mc_spawn_icon_illusioner.png": [98, 111, 155], "mobs_mc_llama_gray.png": [195, 188, 175], "mobs_mc_spawn_icon_zombie.png": [64, 136, 112], "mobs_mc_llama_decor_blue.png": [50, 50, 249], "mobs_mc_spawn_icon_skeleton.png": [146, 146, 146], "mobs_mc_shulker_blue.png": [89, 100, 126], "mobs_mc_shulker_black.png": [78, 75, 76], "mobs_mc_wolf_collar.png": [186, 186, 186], "mobs_mc_spawn_icon_bat.png": [130, 63, 13], "mobs_mc_parrot_green.png": [47, 208, 62], "mobs_mc_llama_decor_magenta.png": [249, 50, 249], "mobs_mc_rabbit_black.png": [73, 64, 61], "mobs_mc_vindicator.png": [56, 56, 57], "mobs_mc_polarbear.png": [233, 220, 208], "mobs_mc_magmacube.png": [83, 40, 27], "mobs_mc_chicken.png": [198, 182, 176], "mobs_mc_ghast_firing.png": [198, 198, 198], "mobs_mc_spawn_icon_zombie_pigman.png": [202, 160, 135], "mobs_mc_husk.png": [98, 95, 76], "mobs_mc_villager_librarian.png": [176, 171, 163], "mobs_mc_villager_priest.png": [100, 64, 74], "mobs_mc_villager_smith.png": [76, 76, 63], "mobs_mc_horse_armor_gold.png": [143, 110, 59], "mobs_mc_spawn_icon_dragon.png": [98, 47, 89], "mobs_mc_spawn_icon_donkey.png": [152, 132, 100], "mobs_mc_squid.png": [37, 52, 68], "mobs_mc_villager_farmer.png": [81, 80, 67], "mobs_mc_spawn_icon_horse_skeleton.png": [245, 204, 202], "mobs_mc_horse_markings_blackdots.png": [24, 22, 22], "mobs_mc_zombie_farmer.png": [119, 99, 85], "mobs_mc_spawn_icon_vex.png": [145, 185, 185], "mobs_mc_parrot_blue.png": [43, 58, 148], "mobs_mc_spider_eyes.png": [174, 48, 48], "mobs_mc_zombie.png": [78, 110, 105], "mobs_mc_llama_decor_light_blue.png": [104, 168, 194], "mobs_mc_zombie_priest.png": [120, 104, 110], "mobs_mc_llama_decor_black.png": [50, 50, 50], "mobs_mc_horse_white.png": [190, 173, 154], "mobs_mc_spawn_icon_vindicator.png": [102, 103, 104], "mobs_mc_silverfish.png": [179, 164, 144], "mobs_mc_llama_decor_gray.png": [98, 98, 98], "mobs_mc_spawn_icon_guardian.png": [119, 156, 148], "mobs_mc_creeper.png": [98, 107, 71], "mobs_mc_shulker_purple.png": [135, 87, 99], "mobs_mc_spawn_icon_rabbit.png": [156, 126, 84], "mobs_mc_horse_armor_iron.png": [134, 123, 118], "mobs_mc_sheep.png": [182, 161, 149], "mobs_mc_parrot_grey.png": [33, 178, 173], "mobs_mc_wolf_icon_sit.png": [8, 88, 116], "mobs_mc_gold_horse_armor.png": [140, 106, 67], "mobs_mc_spawn_icon_witch.png": [98, 85, 68], "mobs_mc_shulker_green.png": [89, 122, 84], "mobs_mc_bat.png": [87, 63, 54], "mobs_mc_horse_chestnut.png": [126, 78, 58], "mobs_mc_shulker_yellow.png": [175, 128, 69], "mobs_mc_spawn_icon_creeper.png": [115, 125, 53], "mobs_mc_slime.png": [63, 133, 78], "mobs_mc_evoker.png": [44, 48, 43], "mobs_mc_horse_skeleton.png": [163, 156, 141], "mobs_mc_spawn_icon_blaze.png": [142, 76, 49], "mobs_mc_shulker_light_blue.png": [114, 140, 158], "mobs_mc_shulker_gray.png": [106, 104, 109], "mobs_mc_horse_darkbrown.png": [69, 47, 34], "mobs_mc_stray_overlay.png": [63, 59, 65], "mobs_mc_arrow_particle.png": [218, 171, 136], "mobs_mc_spawn_icon_cat.png": [120, 66, 10], "mobs_mc_stray.png": [155, 157, 161], "mobs_mc_trading_formspec_bg.png": [157, 157, 157], "mobs_mc_llama_chest.png": [70, 53, 36], "mobs_mc_spawn_icon_villager.png": [134, 124, 81], "mobs_mc_pig.png": [228, 175, 165], "mobs_mc_spawn_icon_mooshroom.png": [160, 56, 55], "mobs_mc_wolf_angry.png": [187, 179, 176], "mobs_mc_cat_black.png": [206, 181, 154], "mobs_mc_vex_charging.png": [142, 153, 153], "mobs_mc_llama.png": [207, 189, 155], "mobs_mc_mushroom_brown.png": [122, 81, 58], "mobs_mc_spawn_icon_shulker.png": [170, 117, 130], "mobs_mc_wither_half_health.png": [7, 58, 91], "mobs_mc_spawn_icon_guardian_elder.png": [174, 140, 113], "mobs_mc_enderman_eyes.png": [184, 211, 242], "mobs_mc_horse_creamy.png": [146, 111, 75], "mobs_mc_spawn_icon_zombie_villager.png": [95, 110, 68], "mobs_mc_vex.png": [128, 162, 162], "mobs_mc_iron_golem.png": [47, 44, 44], "mobs_mc_cat_ocelot.png": [163, 111, 52], "mobs_mc_llama_decor_green.png": [50, 98, 50], "mobs_mc_cow.png": [94, 68, 55], "mobs_mc_llama_decor_brown.png": [101, 75, 60], "mobs_mc_villager_butcher.png": [82, 83, 71], "mobs_mc_parrot_yellow_blue.png": [98, 187, 205], "mobs_mc_zombie_pigman.png": [164, 129, 117], "mobs_mc_spawn_icon_wolf.png": [231, 218, 207], "mobs_mc_zombie_villager.png": [112, 108, 90], "mobs_mc_sheep_fur.png": [203, 186, 174], "mobs_mc_spawn_icon_horse_zombie.png": [129, 143, 66], "mobs_mc_blaze.png": [84, 63, 50], "mcl_totems_totem.png": [185, 139, 52], "mobs_mc_rabbit_salt.png": [122, 99, 87], "mobs_mc_rabbit_white_splotched.png": [146, 139, 135], "mobs_mc_horse_brown.png": [115, 84, 61], "mobs_mc_ghast.png": [199, 199, 199], "mobs_mc_horse_markings_white.png": [165, 149, 132], "mobs_mc_horse_markings_whitefield.png": [193, 178, 162], "mobs_mc_spawn_icon_endermite.png": [138, 67, 74], "mobs_mc_shulker_magenta.png": [143, 97, 130], "mobs_mc_snowman.png": [211, 217, 221], "mobs_mc_zombie_smith.png": [71, 59, 54], "mobs_mc_spawn_icon_squid.png": [55, 58, 103], "mobs_mc_dragon_fireball.png": [89, 66, 79], "mobs_mc_horse_armor_diamond.png": [78, 110, 129], "mobs_mc_diamond_horse_armor.png": [67, 95, 112], "mobs_mc_rabbit_toast.png": [130, 123, 119], "mobs_mc_llama_white.png": [207, 199, 184], "mobs_mc_llama_creamy.png": [208, 190, 155], "mobs_mc_pig_saddle.png": [82, 63, 45], "mobs_mc_spawn_icon_cave_spider.png": [23, 43, 57], "mobs_mc_shulker_silver.png": [140, 138, 143], "mobs_mc_trading_formspec_disabled.png": [193, 26, 26], "mobs_mc_spider.png": [41, 38, 37], "mobs_mc_wither.png": [33, 33, 33], "mobs_mc_llama_decor_white.png": [249, 249, 249], "mobs_mc_witch.png": [80, 74, 67], "mobs_mc_wolf_icon_roam.png": [6, 124, 36], "mobs_mc_illusionist.png": [56, 68, 114], "mobs_mc_endermite.png": [55, 20, 65], "mobs_mc_spawn_icon_witherskeleton.png": [71, 71, 71], "mobs_mc_llama_decor_light_gray.png": [185, 185, 185], "mobs_mc_llama_decor_cyan.png": [18, 249, 249], "mobs_mc_skeleton.png": [124, 124, 124], "mobs_mc_spawn_icon_llama.png": [230, 221, 178], "mobs_mc_spawn_icon_chicken.png": [170, 160, 156], "mobs_mc_shulker_pink.png": [173, 127, 160], "mobs_mc_spawn_icon_spider.png": [53, 43, 43], "mobs_mc_shulker_red.png": [146, 77, 71], "mobs_mc_shulker_white.png": [184, 181, 186], "mobs_mc_spawn_icon_magmacube.png": [52, 33, 23], "mobs_mc_spawn_icon_ghast.png": [212, 212, 212], "mobs_mc_rabbit_brown.png": [112, 86, 73], "mobs_mc_spawn_icon_pig.png": [242, 200, 188], "mobs_mc_spawn_icon_horse.png": [44, 36, 25], "mobs_mc_cat_siamese.png": [161, 144, 133], "mobs_mc_mushroom_red.png": [176, 51, 49], "mobs_mc_shulker_brown.png": [94, 81, 70], "mobs_mc_guardian.png": [78, 116, 130], "mobs_mc_creeper_charge.png": [121, 219, 255], "mobs_mc_villager.png": [88, 91, 55], "mobs_mc_llama_decor_lime.png": [50, 249, 50], "mobs_mc_llama_brown.png": [136, 97, 52], "mobs_mc_parrot_red_blue.png": [171, 70, 37], "mobs_mc_spawn_icon_husk.png": [174, 174, 128], "mobs_mc_rabbit_gold.png": [151, 130, 96], "mobs_mc_spawn_icon_evoker.png": [92, 103, 86], "mobs_mc_iron_horse_armor.png": [133, 119, 114], "mobs_mc_llama_decor_red.png": [249, 50, 50], "mobs_mc_enderman.png": [3, 10, 10], "mobs_mc_mooshroom_brown.png": [93, 50, 28], "mobs_mc_llama_decor_pink.png": [249, 161, 175], "mobs_mc_enderman_block.png": [46, 42, 38], "mobs_mc_mooshroom.png": [90, 42, 41], "mobs_mc_cat_red.png": [221, 163, 120], "mobs_mc_spit.png": [221, 218, 246], "mobs_mc_shulkerbullet.png": [216, 190, 153], "mobs_mc_horse_markings_whitedots.png": [230, 220, 207], "mobs_mc_mule.png": [108, 75, 51], "mobs_mc_spawn_icon_iron_golem.png": [122, 72, 41], "mobs_mc_zombie_butcher.png": [107, 98, 87], "mobs_mc_llama_decor_yellow.png": [249, 249, 50], "mobs_mc_wolf_tame.png": [179, 159, 154], "mobs_mc_horse_gray.png": [78, 68, 62], "mobs_mc_shulker_lime.png": [106, 132, 88], "mobs_mc_rabbit_caerbannog.png": [186, 179, 174], "mobs_mc_zombie_librarian.png": [106, 104, 104], "mobs_mc_spawn_icon_silverfish.png": [199, 168, 128], "mobs_mc_spawn_icon_stray.png": [118, 116, 118], "mobs_mc_spawn_icon_polarbear.png": [237, 235, 212], "mobs_mc_guardian_elder.png": [141, 141, 125], "mobs_mc_spawn_icon_slime.png": [76, 130, 33], "mobs_mc_cave_spider.png": [14, 28, 38], "mobs_mc_spawn_icon_cow.png": [162, 118, 72], "mobs_mc_wolf.png": [182, 165, 159], "mobs_mc_wither_skeleton.png": [50, 50, 50], "mobs_mc_endergolem.png": [135, 87, 99], "mobs_mc_spawn_icon_mule.png": [115, 82, 47], "mobs_mc_llama_decor_orange.png": [249, 131, 50], "mobs_chicken_egg.png": [199, 157, 106], "mobs_mc_rabbit_white.png": [161, 153, 149], "mobs_mc_horse_black.png": [49, 42, 39], "mobs_mc_dragon.png": [79, 54, 67], "mobs_mc_spawn_icon_parrot.png": [202, 100, 54], "mobs_mc_spawn_icon_snowman.png": [216, 173, 147], "mobs_mc_donkey.png": [91, 78, 68], "mobs_mc_shulker_cyan.png": [89, 114, 128], "mobs_mc_spawn_icon_sheep.png": [209, 185, 175], "mobs_mc_TEMP_wither_projectile.png": [69, 69, 69], "mobs_mc_spawn_icon_enderman.png": [63, 82, 87], "mobs_mc_shulker_orange.png": [156, 90, 67], "mobs_mc_empty.png": [255, 255, 255], "mobs_mc_spawn_icon_wither.png": [102, 102, 102], "mcl_boats_spruce_boat.png": [72, 61, 51], "mcl_boats_jungle_boat.png": [102, 73, 58], "mcl_boats_texture_birch_boat.png": [131, 105, 83], "mcl_boats_texture_oak_boat.png": [103, 82, 65], "mcl_boats_birch_boat.png": [120, 95, 78], "mcl_boats_texture_jungle_boat.png": [109, 78, 60], "mcl_boats_oak_boat.png": [93, 76, 62], "mcl_boats_texture_acacia_boat.png": [136, 90, 64], "mcl_boats_texture_dark_oak_boat.png": [89, 76, 64], "mcl_boats_texture_spruce_boat.png": [74, 61, 50], "mcl_boats_acacia_boat.png": [124, 82, 59], "mcl_boats_dark_oak_boat.png": [89, 76, 64], "mobs_nametag.png": [138, 114, 89], "mobs_blood.png": [27, 27, 29], "mcl_minecarts_rail_golden_curved_powered.png": [89, 71, 57], "mcl_minecarts_rail_golden_crossing.png": [83, 70, 55], "mcl_minecarts_rail_detector_curved_powered.png": [81, 68, 64], "mcl_minecarts_rail_golden_t_junction_powered.png": [82, 69, 59], "mcl_minecarts_rail_golden_t_junction.png": [80, 70, 59], "mcl_minecarts_rail_detector.png": [85, 74, 67], "mcl_minecarts_rail_detector_crossing.png": [77, 69, 65], "default_rail_t_junction.png": [79, 68, 61], "mcl_minecarts_rail_activator_crossing_powered.png": [72, 55, 51], "mcl_minecarts_minecart_hopper.png": [45, 45, 45], "mcl_minecarts_minecart_furnace.png": [66, 65, 64], "mcl_minecarts_minecart_command_block.png": [64, 62, 61], "mcl_minecarts_rail_golden.png": [92, 77, 60], "mcl_minecarts_rail_activator_t_junction_powered.png": [76, 61, 55], "default_rail_curved.png": [76, 67, 60], "mcl_minecarts_rail_activator_t_junction.png": [72, 62, 56], "mcl_minecarts_rail_golden_crossing_powered.png": [86, 70, 54], "mcl_minecarts_rail_detector_crossing_powered.png": [78, 68, 64], "mcl_minecarts_rail_detector_curved.png": [77, 70, 66], "default_rail_crossing.png": [79, 68, 59], "mcl_minecarts_rail_detector_t_junction.png": [74, 66, 61], "mcl_minecarts_minecart.png": [72, 60, 51], "mcl_minecarts_rail_golden_curved.png": [85, 73, 58], "mcl_minecarts_rail_activator.png": [78, 64, 56], "mcl_minecarts_rail_activator_powered.png": [86, 62, 54], "mcl_minecarts_rail_detector_t_junction_powered.png": [76, 66, 61], "mcl_minecarts_minecart_normal.png": [47, 45, 43], "mcl_minecarts_minecart_tnt.png": [75, 52, 52], "mcl_minecarts_rail_detector_powered.png": [87, 74, 67], "mcl_minecarts_rail_golden_powered.png": [94, 77, 60], "mcl_minecarts_rail_activator_crossing.png": [65, 56, 52], "default_rail.png": [83, 70, 61], "mcl_minecarts_rail_activator_curved_powered.png": [75, 55, 52], "mcl_minecarts_rail_activator_curved.png": [66, 56, 53], "mcl_minecarts_minecart_chest.png": [51, 48, 46], "mobs_mc_gameconfig_enderman_cactus_background.png": [44, 71, 27], "mcl_paintings_paintings.png": [104, 99, 89], "mcl_paintings_painting.png": [139, 133, 119], "mcl_particles_lava.png": [250, 150, 64], "mcl_particles_instant_effect.png": [160, 160, 160], "mcl_particles_note.png": [41, 40, 39], "mcl_particles_bubble.png": [147, 174, 195], "mcl_particles_sponge1.png": [241, 238, 226], "mcl_particles_smoke_anim.png": [172, 172, 172], "mcl_particles_crit.png": [165, 165, 165], "mcl_particles_mob_death.png": [198, 198, 198], "mcl_particles_droplet_bottle.png": [203, 203, 203], "mcl_particles_sponge4.png": [241, 238, 226], "mcl_particles_effect.png": [184, 184, 184], "mcl_particles_teleport.png": [86, 22, 128], "mcl_particles_sponge5.png": [241, 238, 226], "mcl_particles_flame.png": [244, 149, 63], "mcl_particles_sponge3.png": [241, 238, 226], "mcl_particles_sponge2.png": [241, 238, 226], "mcl_particles_smoke.png": [174, 174, 174], "lightning_lightning_2.png": [255, 255, 255], "lightning_lightning_3.png": [217, 217, 217], "lightning_lightning_1.png": [223, 223, 223], "weather_pack_rain_raindrop_2.png": [33, 79, 142], "weather_pack_rain_raindrop_3.png": [59, 88, 128], "mcl_particles_nether_dust3.png": [143, 105, 102], "weather_pack_rain_raindrop_1.png": [97, 137, 179], "mcl_particles_nether_dust1.png": [143, 105, 102], "weather_pack_snow_snowflake1.png": [255, 255, 255], "mcl_particles_nether_dust2.png": [143, 105, 102], "weather_pack_snow_snowflake2.png": [255, 255, 255], "mcl_moon_moon_phases.png": [80, 106, 141], "hbarmor_bgicon.png": [27, 27, 29], "hbarmor_bar.png": [175, 172, 165], "hbarmor_icon.png": [135, 131, 126], "mcl_base_textures_background9.png": [179, 179, 179], "object_crosshair.png": [255, 255, 255], "bubble.png": [69, 138, 194], "crosshair.png": [255, 255, 255], "heart.png": [137, 47, 40], "mcl_base_textures_background.png": [179, 179, 179], "crack_anylength.png": [93, 93, 93], "mcl_base_textures_button9_pressed.png": [162, 162, 162], "mcl_base_textures_button9.png": [162, 162, 162], "smoke_puff.png": [255, 255, 255], "mineclone2_logo.png": [75, 74, 69], "mineclone2_icon.png": [58, 74, 44], "awards_template.png": [134, 134, 134], "awards_bg_mining.png": [73, 68, 51], "awards_progress_gray.png": [157, 157, 157], "awards_ui_icon.png": [190, 34, 34], "awards_unknown.png": [134, 134, 134], "awards_progress_green.png": [0, 155, 74], "awards_bg_default.png": [38, 38, 38], "hudbars_bar_breath.png": [159, 161, 255], "hudbars_icon_health.png": [137, 47, 40], "hudbars_bar_health.png": [168, 55, 47], "hudbars_bgicon_breath.png": [0, 0, 0], "hudbars_bgicon_health.png": [27, 27, 29], "hudbars_icon_breath.png": [69, 138, 194], "hudbars_bar_background.png": [71, 71, 71], "mcl_achievements_button.png": [158, 152, 67], "mcl_inventory_hotbar.png": [81, 81, 85], "crafting_inventory_creative_survival.png": [195, 195, 195], "crafting_creative_bg_dark.png": [157, 157, 157], "mcl_inventory_empty_armor_slot_shield.png": [25, 32, 34], "crafting_formspec_bg.png": [9, 9, 9], "mcl_inventory_empty_armor_slot_helmet.png": [25, 32, 34], "mcl_inventory_hotbar_selected.png": [113, 85, 40], "crafting_creative_inactive_down.png": [151, 151, 151], "crafting_creative_active_down.png": [196, 196, 196], "crafting_creative_prev.png": [254, 254, 254], "crafting_creative_marker.png": [0, 0, 0], "mcl_inventory_button9_pressed.png": [162, 162, 162], "crafting_creative_active.png": [202, 202, 202], "mcl_inventory_button9.png": [162, 162, 162], "mcl_inventory_empty_armor_slot_chestplate.png": [0, 0, 0], "mcl_inventory_empty_armor_slot_boots.png": [0, 0, 0], "crafting_creative_bg.png": [207, 207, 207], "crafting_creative_inactive.png": [157, 157, 157], "crafting_creative_next.png": [254, 254, 254], "mcl_inventory_empty_armor_slot_leggings.png": [25, 32, 34], "crafting_inventory_creative.png": [206, 206, 206], "crafting_creative_trash.png": [144, 113, 113], "mcl_formspec_itemslot.png": [157, 157, 157], "mcl_experience_bottle.png": [136, 174, 169], "experience_bar_background.png": [49, 46, 45], "experience_orb.png": [93, 174, 0], "experience_bar.png": [74, 102, 70], "mcl_bossbars_empty.png": [255, 255, 255], "mcl_bossbars.png": [76, 68, 75], "mcl_itemframes_item_frame.png": [123, 90, 63], "mcl_itemframes_itemframe_background.png": [136, 104, 75], "mcl_banners_stripe_middle.png": [255, 255, 255], "mcl_banners_skull.png": [255, 255, 255], "mcl_banners_bricks.png": [255, 255, 255], "mcl_banners_square_bottom_left.png": [255, 255, 255], "mcl_banners_gradient.png": [254, 254, 254], "mcl_banners_cross.png": [255, 255, 255], "mcl_banners_gradient_up.png": [254, 254, 254], "mcl_banners_item_overlay.png": [240, 240, 240], "mcl_banners_stripe_downright.png": [255, 255, 255], "mcl_banners_stripe_downleft.png": [255, 255, 255], "mcl_banners_fallback_wood.png": [102, 88, 74], "mcl_banners_base_inverted.png": [255, 255, 255], "mcl_banners_triangles_top.png": [255, 255, 255], "mcl_banners_banner_base.png": [215, 206, 193], "mcl_banners_curly_border.png": [254, 254, 254], "mcl_banners_thing.png": [253, 253, 253], "mcl_banners_small_stripes.png": [255, 255, 255], "mcl_banners_triangle_bottom.png": [254, 254, 254], "mcl_banners_stripe_right.png": [255, 255, 255], "mcl_banners_straight_cross.png": [255, 255, 255], "mcl_banners_triangle_top.png": [255, 255, 255], "mcl_banners_border.png": [255, 255, 255], "mcl_banners_diagonal_left.png": [255, 255, 255], "mcl_banners_diagonal_right.png": [255, 255, 255], "mcl_banners_base.png": [255, 255, 255], "mcl_banners_half_vertical.png": [255, 255, 255], "mcl_banners_circle.png": [254, 254, 254], "mcl_banners_triangles_bottom.png": [255, 255, 255], "mcl_banners_item_base.png": [103, 89, 75], "mcl_banners_stripe_left.png": [255, 255, 255], "mcl_banners_rhombus.png": [255, 255, 255], "mcl_banners_creeper.png": [255, 255, 255], "mcl_banners_flower.png": [254, 254, 254], "mcl_banners_stripe_bottom.png": [255, 255, 255], "mcl_banners_half_horizontal.png": [255, 255, 255], "mcl_banners_half_horizontal_bottom.png": [255, 255, 255], "mcl_banners_square_top_left.png": [255, 255, 255], "mcl_banners_square_top_right.png": [255, 255, 255], "mcl_banners_stripe_center.png": [255, 255, 255], "mcl_banners_diagonal_up_left.png": [255, 255, 255], "mcl_banners_stripe_top.png": [255, 255, 255], "mcl_banners_diagonal_up_right.png": [255, 255, 255], "mcl_banners_square_bottom_right.png": [255, 255, 255], "mcl_banners_half_vertical_right.png": [255, 255, 255], "mcl_doors_trapdoor_dark_oak.png": [81, 68, 56], "mcl_doors_trapdoor_acacia_side.png": [154, 102, 71], "doors_trapdoor_steel_side.png": [149, 140, 140], "mcl_doors_door_jungle_side_upper.png": [109, 75, 57], "mcl_doors_door_dark_oak_side_lower.png": [103, 90, 75], "mcl_doors_door_iron_lower.png": [157, 152, 151], "mcl_doors_door_acacia_upper.png": [152, 100, 69], "mcl_doors_door_jungle_side_lower.png": [107, 72, 55], "mcl_doors_door_wood_lower.png": [89, 70, 55], "doors_trapdoor_steel.png": [149, 140, 140], "mcl_doors_door_iron_side_upper.png": [155, 149, 148], "mcl_doors_door_acacia_side_upper.png": [133, 80, 53], "mcl_doors_door_jungle.png": [116, 83, 62], "mcl_doors_door_iron_side_lower.png": [157, 152, 151], "mcl_doors_door_birch_upper.png": [179, 158, 139], "mcl_doors_trapdoor_spruce_side.png": [73, 59, 47], "mcl_doors_door_iron_upper.png": [155, 149, 148], "mcl_doors_door_spruce_side_lower.png": [92, 79, 68], "mcl_doors_trapdoor_spruce.png": [71, 57, 46], "mcl_doors_trapdoor_birch_side.png": [147, 116, 89], "doors_trapdoor_side.png": [113, 86, 67], "mcl_doors_door_acacia_lower.png": [153, 101, 70], "mcl_doors_door_dark_oak_side_upper.png": [102, 89, 75], "mcl_doors_door_acacia_side_lower.png": [131, 78, 51], "mcl_doors_door_wood_upper.png": [92, 72, 57], "mcl_doors_trapdoor_birch.png": [173, 151, 132], "mcl_doors_door_dark_oak_upper.png": [83, 71, 59], "mcl_doors_door_acacia.png": [148, 98, 67], "mcl_doors_door_spruce.png": [67, 56, 47], "mcl_doors_door_spruce_lower.png": [71, 58, 48], "mcl_doors_door_birch_side_upper.png": [153, 121, 94], "mcl_doors_trapdoor_dark_oak_side.png": [85, 72, 60], "mcl_doors_door_wood_side_upper.png": [84, 65, 51], "mcl_doors_door_birch.png": [172, 147, 124], "mcl_doors_door_birch_lower.png": [165, 140, 119], "mcl_doors_trapdoor_jungle.png": [103, 70, 52], "doors_item_steel.png": [148, 144, 143], "doors_trapdoor.png": [98, 75, 59], "mcl_doors_door_jungle_lower.png": [116, 82, 61], "doors_item_wood.png": [88, 67, 53], "mcl_doors_door_jungle_upper.png": [113, 79, 59], "mcl_doors_door_spruce_upper.png": [71, 58, 47], "mcl_doors_door_dark_oak_lower.png": [84, 71, 59], "mcl_doors_door_dark_oak.png": [82, 69, 57], "mcl_doors_door_wood_side_lower.png": [132, 102, 81], "mcl_doors_trapdoor_jungle_side.png": [121, 87, 62], "mcl_doors_door_spruce_side_upper.png": [92, 79, 68], "mcl_doors_door_birch_side_lower.png": [152, 119, 92], "mcl_doors_trapdoor_acacia.png": [148, 96, 66], "mcl_fishing_clownfish_raw.png": [205, 127, 81], "mcl_fishing_fish_raw.png": [70, 112, 154], "mcl_fishing_salmon_raw.png": [112, 105, 102], "mcl_fishing_fish_cooked.png": [93, 84, 94], "mcl_fishing_bobber.png": [171, 117, 119], "mcl_fishing_pufferfish_raw.png": [219, 165, 77], "mcl_fishing_fishing_rod.png": [134, 116, 103], "mcl_fishing_salmon_cooked.png": [97, 91, 89], "mcl_stairs_diorite_smooth_slab.png": [156, 153, 151], "mcl_stairs_iron_block_slab.png": [166, 159, 159], "mcl_stairs_andesite_smooth_slab.png": [106, 113, 108], "mcl_stairs_gold_block_slab.png": [191, 146, 56], "mcl_stairs_granite_smooth_slab.png": [150, 121, 109], "mcl_stairs_lapis_block_slab.png": [49, 89, 158], "mcl_fireworks_rocket.png": [155, 84, 71], "mcl_bows_arrow_inv.png": [144, 129, 121], "mcl_bows_arrow_overlay.png": [193, 191, 186], "mcl_bows_bow_1.png": [112, 95, 79], "mcl_bows_bow_0.png": [111, 94, 79], "mcl_bows_bow_2.png": [115, 98, 82], "mcl_bows_bow.png": [114, 95, 78], "mcl_bows_arrow.png": [133, 116, 108], "mcl_bows_arrow_front.png": [178, 175, 168], "mcl_bows_arrow_back.png": [218, 216, 213], "mcl_ocean_dead_bubble_coral.png": [118, 108, 126], "mcl_ocean_tube_coral.png": [57, 88, 209], "mcl_ocean_sea_pickle_2_anim.png": [95, 122, 51], "mcl_ocean_dead_horn_coral_fan.png": [150, 143, 123], "mcl_ocean_dead_bubble_coral_block.png": [114, 105, 122], "mcl_ocean_sea_pickle_3_off.png": [68, 99, 36], "mcl_ocean_dead_horn_coral_block.png": [152, 146, 125], "mcl_ocean_bubble_coral_block.png": [143, 76, 195], "mcl_ocean_horn_coral.png": [233, 195, 69], "mcl_ocean_dead_tube_coral_block.png": [99, 104, 127], "mcl_ocean_sea_pickle_item.png": [93, 120, 50], "mcl_ocean_kelp_item.png": [42, 105, 55], "mcl_ocean_dried_kelp_side.png": [71, 80, 67], "mcl_ocean_dead_tube_coral.png": [99, 105, 128], "mcl_ocean_fire_coral_block.png": [198, 74, 62], "mcl_ocean_bubble_coral.png": [149, 77, 200], "mcl_ocean_prismarine_bricks.png": [104, 112, 115], "mcl_ocean_brain_coral.png": [206, 87, 153], "mcl_ocean_dried_kelp_top.png": [56, 71, 57], "mcl_ocean_brain_coral_block.png": [200, 85, 148], "mcl_ocean_prismarine_dark.png": [77, 89, 97], "mcl_ocean_dead_fire_coral_block.png": [127, 102, 100], "mcl_ocean_prismarine_shard.png": [122, 144, 135], "mcl_ocean_sea_pickle_2_off.png": [70, 100, 36], "mcl_ocean_sea_pickle_4_anim.png": [85, 113, 46], "mcl_ocean_dead_brain_coral.png": [134, 117, 127], "mcl_ocean_tube_coral_fan.png": [59, 85, 203], "mcl_ocean_sea_pickle_4_off.png": [68, 98, 36], "mcl_ocean_sea_pickle_1_anim.png": [106, 132, 57], "mcl_ocean_fire_coral.png": [208, 78, 65], "mcl_ocean_sea_pickle_3_anim.png": [89, 116, 48], "mcl_ocean_dead_fire_coral_fan.png": [140, 113, 110], "mcl_ocean_prismarine_crystals.png": [182, 193, 190], "mcl_ocean_prismarine_anim.png": [104, 123, 122], "mcl_ocean_horn_coral_fan.png": [230, 189, 68], "mcl_ocean_dead_tube_coral_fan.png": [98, 103, 125], "mcl_ocean_sea_pickle_1_off.png": [72, 103, 37], "mcl_ocean_dead_horn_coral.png": [154, 148, 127], "mcl_ocean_dead_fire_coral.png": [133, 107, 105], "mcl_ocean_bubble_coral_fan.png": [141, 75, 192], "mcl_ocean_horn_coral_block.png": [232, 193, 69], "mcl_ocean_brain_coral_fan.png": [206, 87, 154], "mcl_ocean_sea_lantern.png": [133, 144, 145], "mcl_ocean_seagrass.png": [48, 125, 60], "mcl_ocean_dead_brain_coral_fan.png": [134, 117, 127], "mcl_ocean_dried_kelp.png": [36, 57, 40], "mcl_ocean_dead_bubble_coral_fan.png": [113, 104, 120], "mcl_ocean_dried_kelp_bottom.png": [56, 71, 57], "mcl_ocean_kelp_plant.png": [42, 105, 55], "mcl_ocean_tube_coral_block.png": [58, 88, 207], "mcl_ocean_dead_brain_coral_block.png": [130, 114, 123], "mcl_ocean_fire_coral_fan.png": [205, 77, 64], "mcl_portals_endframe_bottom.png": [109, 99, 87], "mcl_portals_particle3.png": [146, 0, 201], "mcl_portals_particle2.png": [146, 0, 201], "mcl_portals_endframe_top.png": [95, 85, 74], "mcl_portals_particle4.png": [146, 0, 201], "mcl_portals_endframe_eye.png": [135, 36, 18], "mcl_portals_end_portal.png": [14, 14, 14], "mcl_particles_nether_portal.png": [206, 0, 206], "mcl_portals_particle5.png": [189, 11, 213], "mcl_portals_endframe_side.png": [110, 99, 86], "mcl_portals_particle1.png": [173, 28, 229], "mcl_portals_portal.png": [74, 24, 172], "mcl_particles_nether_portal_t.png": [159, 0, 223], "cake_side.png": [201, 170, 155], "cake_inner.png": [185, 129, 99], "cake_bottom.png": [160, 86, 51], "cake_top.png": [241, 228, 226], "cake.png": [216, 187, 176], "mcl_cocoas_cocoa_top_stage_2.png": [138, 68, 52], "mcl_cocoas_cocoa_stage_1.png": [172, 121, 69], "mcl_cocoas_cocoa_stage_2.png": [132, 65, 50], "mcl_cocoas_cocoa_stage_0.png": [65, 77, 39], "mcl_fences_fence_red_nether_brick.png": [68, 17, 0], "mcl_fences_fence_gate_red_nether_brick.png": [64, 15, 0], "mcl_fences_fence_gate_nether_brick.png": [50, 25, 26], "mcl_mobitems_spider_eye.png": [154, 69, 60], "mcl_mobitems_leather.png": [105, 75, 45], "mcl_mobitems_feather.png": [206, 185, 183], "mcl_mobitems_string.png": [202, 186, 166], "mcl_mobitems_rabbit_foot.png": [124, 107, 97], "mcl_mobitems_saddle.png": [93, 72, 50], "mcl_mobitems_bone.png": [182, 162, 139], "mcl_mobitems_shulker_shell.png": [118, 68, 83], "mcl_mobitems_blaze_rod.png": [143, 64, 28], "mcl_mobitems_beef_raw.png": [147, 63, 54], "mcl_mobitems_rabbit_stew.png": [127, 98, 79], "mcl_mobitems_rotten_flesh.png": [110, 68, 45], "mcl_mobitems_chicken_raw.png": [217, 178, 149], "mcl_mobitems_ghast_tear.png": [148, 160, 166], "mcl_mobitems_porkchop_raw.png": [160, 72, 69], "mcl_mobitems_rabbit_hide.png": [108, 85, 73], "mcl_mobitems_slimeball.png": [75, 134, 82], "mcl_mobitems_magma_cream.png": [102, 54, 34], "default_gunpowder.png": [48, 41, 36], "mcl_mobitems_chicken_cooked.png": [187, 145, 106], "mcl_mobitems_beef_cooked.png": [112, 70, 49], "mcl_mobitems_rabbit_cooked.png": [188, 155, 131], "mcl_mobitems_blaze_powder.png": [86, 50, 34], "mcl_mobitems_rabbit_raw.png": [217, 177, 157], "mcl_mobitems_carrot_on_a_stick.png": [133, 113, 93], "mcl_mobitems_mutton_cooked.png": [144, 104, 77], "mcl_mobitems_nether_star.png": [234, 189, 123], "mcl_mobitems_porkchop_cooked.png": [116, 72, 48], "mcl_mobitems_mutton_raw.png": [175, 77, 77], "mcl_mobitems_bucket_milk.png": [180, 175, 166], "mcl_farming_wheat_stage_0.png": [53, 101, 46], "farming_carrot.png": [147, 106, 63], "farming_potato_poison.png": [121, 93, 55], "farming_cookie.png": [144, 100, 61], "mcl_farming_melon_seeds.png": [100, 72, 61], "mcl_farming_potatoes_stage_1.png": [69, 113, 61], "mcl_farming_melon_stem_disconnected.png": [96, 96, 96], "farming_carrot_4.png": [93, 105, 58], "mcl_farming_wheat_stage_5.png": [101, 142, 66], "farming_tool_woodhoe.png": [120, 101, 86], "mcl_farming_potatoes_stage_0.png": [73, 119, 65], "farming_carrot_1.png": [75, 112, 61], "farming_carrot_3.png": [70, 107, 57], "farming_melon.png": [153, 84, 62], "mcl_farming_pumpkin_seeds.png": [132, 120, 87], "farming_wheat_harvested.png": [178, 134, 80], "farming_pumpkin_side.png": [186, 100, 42], "mcl_farming_pumpkin_face.png": [181, 94, 40], "mcl_farming_wheat_stage_4.png": [86, 129, 65], "mcl_farming_farmland_wet.png": [69, 55, 46], "mcl_farming_beetroot_0.png": [56, 122, 75], "mcl_farming_pumpkin_stem_connected.png": [94, 94, 94], "mcl_farming_farmland_dry.png": [101, 80, 68], "farming_tool_diamondhoe.png": [101, 104, 104], "mcl_farming_beetroot_1.png": [54, 118, 72], "mcl_farming_beetroot_2.png": [54, 119, 73], "mcl_farming_wheat_stage_7.png": [165, 116, 75], "mcl_farming_beetroot.png": [113, 69, 66], "mcl_farming_wheat_stage_6.png": [145, 145, 69], "mcl_farming_wheat_stage_3.png": [64, 113, 52], "mcl_farming_pumpkin_stem_disconnected.png": [96, 96, 96], "mcl_farming_hayblock_top.png": [154, 116, 81], "farming_pumpkin_face_light.png": [189, 100, 45], "farming_potato_baked.png": [118, 84, 45], "farming_melon_side.png": [68, 95, 37], "farming_potato.png": [107, 74, 39], "mcl_farming_wheat_stage_1.png": [49, 97, 45], "farming_pumpkin_top.png": [172, 87, 40], "farming_bread.png": [177, 133, 94], "mcl_farming_beetroot_soup.png": [120, 70, 63], "farming_melon_top.png": [58, 80, 33], "mcl_farming_potatoes_stage_3.png": [82, 106, 57], "farming_tool_stonehoe.png": [133, 122, 111], "mcl_farming_beetroot_seeds.png": [107, 104, 88], "farming_tool_goldhoe.png": [162, 131, 70], "farming_carrot_gold.png": [140, 122, 48], "farming_carrot_2.png": [72, 108, 58], "farming_pumpkin_face.png": [161, 79, 37], "mcl_farming_melon_stem_connected.png": [94, 94, 94], "mcl_farming_pumpkin_pie.png": [172, 98, 45], "mcl_farming_pumpkin_face_preview.png": [166, 81, 38], "mcl_farming_wheat_stage_2.png": [49, 97, 45], "farming_tool_steelhoe.png": [123, 112, 102], "mcl_farming_potatoes_stage_2.png": [72, 116, 62], "mcl_farming_beetroot_3.png": [73, 105, 71], "mcl_farming_wheat_seeds.png": [102, 87, 55], "mcl_farming_hayblock_side.png": [135, 99, 71], "mcl_end_purpur_block.png": [161, 111, 175], "mcl_end_chorus_flower_dead.png": [82, 79, 118], "mcl_end_end_stone.png": [221, 214, 130], "mcl_end_endframe_side.png": [110, 99, 86], "mcl_end_purpur_pillar.png": [157, 108, 171], "mcl_end_chorus_fruit.png": [87, 89, 121], "mcl_end_endframe_eye.png": [135, 36, 18], "mcl_end_chorus_fruit_popped.png": [70, 67, 110], "mcl_end_end_rod_top.png": [123, 75, 97], "mcl_end_endframe_top.png": [95, 85, 74], "mcl_end_purpur_pillar_top.png": [159, 110, 173], "mcl_end_chorus_flower.png": [92, 92, 125], "mcl_end_crystal_item.png": [170, 140, 162], "mcl_end_end_bricks.png": [194, 187, 123], "mcl_end_dragon_egg.png": [55, 34, 32], "mcl_end_ender_eye.png": [130, 33, 17], "mcl_end_chorus_plant.png": [78, 73, 115], "mcl_end_end_rod_bottom.png": [122, 74, 96], "mcl_end_crystal_beam.png": [251, 251, 251], "mcl_end_end_rod_side.png": [242, 202, 177], "mcl_clock_clock_18.png": [152, 123, 81], "mcl_clock_clock_03.png": [160, 129, 88], "mcl_clock_clock_49.png": [155, 122, 79], "mcl_clock_clock_34.png": [140, 115, 76], "mcl_clock_clock_01.png": [161, 129, 88], "mcl_clock_clock_32.png": [141, 116, 77], "mcl_clock_clock_27.png": [142, 117, 78], "mcl_clock_clock_42.png": [147, 119, 79], "mcl_clock_clock_25.png": [145, 119, 78], "mcl_clock_clock_56.png": [160, 126, 81], "mcl_clock_clock_22.png": [146, 119, 79], "mcl_clock_clock_31.png": [141, 116, 76], "mcl_clock_clock_57.png": [161, 127, 83], "mcl_clock_clock_58.png": [157, 127, 86], "mcl_clock_clock_39.png": [146, 119, 79], "mcl_clock_clock_59.png": [160, 128, 86], "mcl_clock_clock_16.png": [157, 125, 80], "mcl_clock_clock_38.png": [141, 117, 78], "mcl_clock_clock_53.png": [158, 124, 80], "mcl_clock_clock_43.png": [149, 121, 80], "mcl_clock_clock_09.png": [161, 127, 81], "mcl_clock_clock_33.png": [141, 116, 76], "mcl_clock_clock_07.png": [162, 128, 83], "mcl_clock_clock_23.png": [148, 121, 80], "mcl_clock_clock_51.png": [156, 123, 80], "mcl_clock_clock_10.png": [158, 127, 85], "mcl_clock_clock_55.png": [160, 126, 81], "mcl_clock_clock_46.png": [152, 122, 81], "mcl_clock_clock_26.png": [142, 117, 79], "mcl_clock_clock_06.png": [157, 127, 86], "mcl_clock_clock_00.png": [162, 129, 87], "mcl_clock_clock_28.png": [141, 116, 77], "mcl_clock_clock_44.png": [150, 120, 79], "mcl_clock_clock_08.png": [160, 127, 81], "mcl_clock_clock_19.png": [152, 122, 80], "mcl_clock_clock_12.png": [159, 127, 83], "mcl_clock_clock_45.png": [153, 123, 81], "mcl_clock_clock_24.png": [147, 120, 80], "mcl_clock_clock_15.png": [157, 125, 81], "mcl_clock_clock_20.png": [150, 121, 79], "mcl_clock_clock_61.png": [160, 129, 88], "mcl_clock_clock_02.png": [159, 129, 89], "mcl_clock_clock_40.png": [147, 120, 79], "mcl_clock_clock_37.png": [143, 118, 79], "mcl_clock_clock_48.png": [155, 123, 79], "mcl_clock_clock_13.png": [159, 126, 82], "mcl_clock_clock_17.png": [156, 125, 81], "mcl_clock_clock_52.png": [156, 123, 80], "mcl_clock_clock_54.png": [156, 125, 84], "mcl_clock_clock_04.png": [159, 128, 87], "mcl_clock_clock_47.png": [154, 122, 80], "mcl_clock_clock_62.png": [159, 129, 89], "mcl_clock_clock_41.png": [147, 120, 79], "mcl_clock_clock_35.png": [140, 115, 76], "mcl_clock_clock_60.png": [159, 128, 87], "mcl_clock_clock_50.png": [155, 123, 80], "mcl_clock_clock_29.png": [142, 117, 78], "mcl_clock_clock_21.png": [150, 122, 81], "mcl_clock_clock_30.png": [140, 115, 76], "mcl_clock_clock_14.png": [157, 125, 81], "mcl_clock_clock_05.png": [160, 128, 85], "mcl_clock_clock_36.png": [141, 116, 77], "mcl_clock_clock_63.png": [161, 129, 88], "mcl_clock_clock_11.png": [160, 127, 82], "mcl_compass_compass_02.png": [116, 107, 104], "mcl_compass_compass_06.png": [117, 107, 104], "mcl_compass_compass_04.png": [117, 106, 104], "mcl_compass_compass_19.png": [116, 106, 103], "mcl_compass_compass_16.png": [114, 106, 104], "mcl_compass_compass_26.png": [117, 107, 104], "mcl_compass_compass_25.png": [117, 107, 105], "mcl_compass_compass_24.png": [117, 107, 105], "mcl_compass_compass_17.png": [115, 106, 104], "mcl_compass_compass_23.png": [117, 107, 105], "mcl_compass_compass_01.png": [115, 107, 104], "mcl_compass_compass_28.png": [116, 107, 104], "mcl_compass_compass_05.png": [117, 106, 104], "mcl_compass_compass_09.png": [117, 107, 104], "mcl_compass_compass_10.png": [117, 107, 105], "mcl_compass_compass_14.png": [116, 107, 105], "mcl_compass_compass_18.png": [117, 107, 104], "mcl_compass_compass_13.png": [117, 106, 104], "mcl_compass_compass_08.png": [117, 107, 104], "mcl_compass_compass_21.png": [117, 107, 104], "mcl_compass_compass_27.png": [117, 106, 104], "mcl_compass_compass_30.png": [116, 107, 104], "mcl_compass_compass_15.png": [115, 106, 104], "mcl_compass_compass_29.png": [115, 106, 104], "mcl_compass_compass_03.png": [116, 106, 104], "mcl_compass_compass_07.png": [117, 107, 104], "mcl_compass_compass_22.png": [117, 107, 105], "mcl_compass_compass_12.png": [117, 106, 104], "mcl_compass_compass_00.png": [114, 107, 104], "mcl_compass_compass_20.png": [116, 106, 104], "mcl_compass_compass_31.png": [115, 107, 104], "mcl_compass_compass_11.png": [117, 106, 104], "mcl_jukebox_record_wait.png": [39, 42, 55], "mcl_jukebox_record_cat.png": [40, 45, 51], "mcl_jukebox_record_mellohi.png": [46, 44, 59], "mcl_jukebox_record_13.png": [51, 47, 51], "mcl_jukebox_record_ward.png": [39, 43, 51], "mcl_jukebox_record_chirp.png": [49, 40, 50], "mcl_jukebox_record_blocks.png": [47, 37, 49], "mcl_jukebox_record_11.png": [41, 40, 52], "mcl_jukebox_record_mall.png": [42, 41, 62], "mcl_jukebox_top.png": [72, 56, 44], "mcl_jukebox_record_strad.png": [45, 45, 57], "mcl_jukebox_record_far.png": [47, 48, 52], "mcl_jukebox_side.png": [94, 74, 57], "mcl_jukebox_record_stal.png": [39, 38, 49], "mcl_fences_fence_acacia.png": [152, 99, 68], "mcl_fences_fence_gate_mask.png": [255, 126, 126], "mcl_fences_fence_gate_spruce.png": [85, 69, 56], "mcl_fences_fence_big_oak.png": [83, 71, 59], "mcl_fences_fence_spruce.png": [84, 67, 54], "mcl_fences_fence_gate_birch.png": [153, 121, 94], "mcl_fences_fence_gate_acacia.png": [155, 102, 70], "mcl_fences_fence_gate_big_oak.png": [85, 73, 61], "mcl_fences_fence_oak.png": [108, 83, 64], "mcl_fences_fence_gate_oak.png": [111, 85, 66], "mcl_fences_fence_jungle.png": [115, 80, 60], "mcl_fences_fence_nether_brick.png": [49, 24, 24], "mcl_fences_fence_birch.png": [151, 119, 93], "mcl_fences_fence_gate_jungle.png": [117, 82, 61], "mcl_fences_fence_mask.png": [255, 126, 126], "mcl_core_leaves_birch.png": [28, 57, 28], "default_mossycobble.png": [100, 105, 94], "default_flint.png": [70, 67, 64], "mcl_core_bowl.png": [78, 61, 47], "mcl_core_bone_block_top.png": [220, 201, 170], "default_acacia_tree.png": [105, 91, 74], "default_steel_block.png": [159, 151, 151], "mcl_core_stonebrick_mossy.png": [81, 101, 76], "default_diamond_block.png": [92, 160, 200], "default_leaves.png": [39, 79, 38], "mcl_core_web.png": [202, 189, 167], "mcl_core_reeds.png": [57, 100, 52], "default_gold_ingot.png": [179, 133, 47], "mcl_core_grass_path_side.png": [113, 89, 62], "mcl_core_red_sand.png": [224, 137, 111], "default_apple.png": [137, 57, 44], "mcl_core_log_birch_top.png": [155, 130, 112], "default_coal_block.png": [51, 49, 51], "mcl_core_andesite_smooth.png": [107, 113, 109], "mcl_core_apple_golden.png": [176, 138, 51], "mcl_core_diorite.png": [153, 149, 146], "mcl_core_granite_smooth.png": [150, 121, 110], "mcl_core_bedrock.png": [91, 77, 66], "mcl_core_planks_spruce.png": [81, 65, 54], "mcl_core_sapling_big_oak.png": [69, 92, 80], "mcl_core_emerald_ore.png": [115, 122, 103], "mcl_core_sandstone_smooth.png": [202, 155, 121], "mcl_core_glass_light_blue.png": [101, 153, 215], "default_brick.png": [139, 87, 75], "mcl_core_redstone_ore.png": [128, 91, 88], "mcl_core_cactus_top.png": [77, 99, 49], "mcl_core_frosted_ice_1.png": [147, 198, 227], "mcl_core_sapling_spruce.png": [55, 72, 53], "mcl_core_stripped_acacia_top.png": [149, 92, 58], "mcl_core_log_spruce_top.png": [97, 71, 57], "mcl_core_glass_lime.png": [126, 203, 24], "mcl_core_lapis_ore.png": [111, 113, 125], "default_junglesapling.png": [64, 88, 39], "default_clay_brick.png": [127, 57, 48], "default_gold_block.png": [192, 147, 59], "default_water_source_animated.png": [37, 98, 129], "mcl_core_glass_yellow.png": [228, 228, 50], "default_acacia_sapling.png": [109, 92, 59], "mcl_core_stripped_acacia_side.png": [155, 96, 61], "mcl_core_sandstone_carved.png": [199, 152, 119], "mcl_core_glass_blue.png": [50, 75, 178], "mcl_core_red_sandstone_normal.png": [198, 120, 104], "mcl_core_glass_gray.png": [75, 75, 75], "mcl_core_leaves_spruce.png": [38, 74, 47], "mcl_core_glass_pink.png": [241, 126, 164], "mcl_core_lapis_block.png": [50, 92, 162], "mcl_core_glass_purple.png": [126, 62, 178], "mcl_core_iron_nugget.png": [156, 151, 145], "default_papyrus.png": [82, 114, 57], "default_dry_grass.png": [100, 94, 54], "mcl_core_stripped_dark_oak_top.png": [91, 78, 68], "mcl_core_glass_silver.png": [153, 153, 153], "mcl_core_andesite.png": [104, 110, 107], "mcl_core_frosted_ice_3.png": [165, 209, 233], "mcl_core_sugar.png": [215, 215, 215], "default_acacia_wood.png": [152, 100, 69], "mcl_core_glass_black.png": [24, 24, 24], "mcl_core_iron_ore.png": [134, 123, 117], "mcl_core_stripped_birch_side.png": [163, 130, 104], "default_clay.png": [124, 124, 124], "mcl_core_stripped_jungle_side.png": [140, 98, 76], "mcl_core_glass_red.png": [153, 50, 50], "mcl_core_grass_block_top.png": [141, 130, 113], "mcl_core_planks_birch.png": [145, 113, 89], "mcl_core_glass_white.png": [254, 254, 254], "mcl_core_stripped_oak_side.png": [119, 94, 71], "mcl_core_glass_cyan.png": [75, 126, 153], "mcl_core_cactus_side.png": [88, 110, 56], "default_ladder.png": [83, 64, 50], "default_dry_grass_side.png": [91, 93, 52], "mcl_core_stripped_jungle_top.png": [143, 101, 78], "mcl_core_ice_packed.png": [165, 211, 231], "mcl_core_frosted_ice_2.png": [153, 202, 229], "default_dry_shrub.png": [118, 88, 69], "mcl_core_red_sandstone_carved.png": [202, 122, 104], "default_tree.png": [95, 75, 57], "default_clay_lump.png": [111, 111, 111], "mcl_core_red_sandstone_top.png": [212, 126, 108], "mcl_core_dirt_podzol_side.png": [101, 79, 63], "mcl_core_red_sandstone_smooth.png": [207, 124, 106], "default_jungletree_top.png": [125, 87, 67], "mcl_core_coal_ore.png": [109, 101, 99], "default_jungleleaves.png": [29, 84, 30], "mcl_core_vine.png": [21, 61, 21], "default_snow.png": [221, 229, 234], "mcl_core_leaves_big_oak.png": [21, 69, 28], "mcl_core_void.png": [59, 59, 59], "default_tree_top.png": [135, 104, 74], "mcl_core_gold_ore.png": [132, 119, 103], "default_steel_ingot.png": [142, 137, 131], "default_sapling.png": [62, 90, 45], "mcl_core_log_birch.png": [194, 184, 174], "mcl_core_stripped_spruce_top.png": [111, 81, 64], "default_water_flowing_animated.png": [38, 101, 129], "mcl_core_emerald_block.png": [44, 138, 39], "default_jungletree.png": [86, 58, 45], "mcl_core_grass_side_snowed.png": [162, 154, 150], "default_stone_brick.png": [97, 89, 86], "default_lava_flowing_animated.png": [177, 42, 16], "mcl_core_stripped_spruce_side.png": [104, 78, 63], "default_coal_lump.png": [41, 39, 41], "default_sand.png": [220, 170, 127], "mcl_core_glass_green.png": [101, 126, 50], "mcl_core_glass_orange.png": [215, 126, 50], "default_acacia_tree_top.png": [130, 84, 55], "mcl_core_stripped_oak_top.png": [139, 108, 78], "mcl_core_grass_block_side_overlay.png": [153, 142, 123], "default_lava_source_animated.png": [180, 45, 17], "mcl_core_cactus_bottom.png": [169, 168, 116], "mcl_core_sandstone_bottom.png": [202, 155, 121], "default_paper.png": [213, 184, 154], "mcl_core_diamond_ore.png": [122, 124, 126], "default_ice.png": [145, 197, 226], "mcl_core_dirt_podzol_top.png": [85, 63, 42], "mcl_core_slime.png": [93, 157, 86], "mcl_core_gold_nugget.png": [213, 169, 74], "default_stick.png": [88, 70, 57], "mcl_core_emerald.png": [59, 160, 52], "default_diamond.png": [109, 179, 217], "mcl_core_mycelium_top.png": [108, 89, 117], "mcl_core_bone_block_side.png": [226, 207, 174], "mcl_core_diorite_smooth.png": [157, 154, 152], "default_obsidian.png": [13, 9, 25], "mcl_core_planks_big_oak.png": [87, 74, 62], "mcl_core_log_spruce.png": [66, 51, 44], "mcl_core_glass_magenta.png": [178, 75, 215], "mcl_core_granite.png": [153, 121, 110], "mcl_core_log_big_oak_top.png": [83, 70, 62], "default_cobble.png": [113, 106, 104], "mcl_core_red_sandstone_bottom.png": [207, 124, 106], "mcl_core_barrier.png": [138, 46, 38], "mcl_core_stripped_dark_oak_side.png": [86, 73, 63], "mcl_core_mycelium_side.png": [107, 84, 87], "mcl_core_stonebrick_cracked.png": [94, 87, 83], "mcl_core_charcoal.png": [40, 35, 32], "mcl_core_glass_brown.png": [101, 75, 50], "mcl_core_stonebrick_carved.png": [97, 90, 85], "default_wood.png": [113, 87, 67], "default_dirt.png": [108, 83, 70], "mcl_core_log_big_oak.png": [74, 62, 55], "default_junglewood.png": [113, 78, 59], "mcl_core_frosted_ice_0.png": [140, 193, 224], "mcl_core_sandstone_normal.png": [195, 149, 117], "default_gravel.png": [112, 105, 99], "mcl_core_sandstone_top.png": [201, 154, 121], "default_glass.png": [213, 223, 235], "default_stone.png": [130, 122, 118], "mcl_core_sapling_birch.png": [78, 110, 74], "mcl_core_coarse_dirt.png": [117, 92, 76], "default_acacia_leaves.png": [110, 89, 45], "mcl_core_stripped_birch_top.png": [157, 126, 102], "mcl_core_grass_path_top.png": [125, 101, 50], "mcl_throwing_ender_pearl.png": [78, 19, 26], "mcl_throwing_egg.png": [199, 157, 106], "mcl_throwing_snowball.png": [191, 200, 203], "mcl_flowers_tulip_red.png": [82, 57, 43], "mcl_flowers_double_plant_rose_top.png": [81, 69, 45], "mcl_flowers_double_plant_sunflower_front.png": [203, 157, 61], "mcl_flowers_tulip_white.png": [106, 122, 95], "mcl_flowers_double_plant_grass_top.png": [156, 145, 125], "mcl_flowers_azure_bluet.png": [97, 114, 98], "mcl_flowers_oxeye_daisy.png": [130, 139, 110], "mcl_flowers_poppy.png": [96, 59, 43], "mcl_flowers_double_plant_paeonia_top.png": [90, 84, 81], "mcl_flowers_double_plant_rose_bottom.png": [78, 63, 41], "mcl_flowers_tallgrass.png": [151, 141, 122], "mcl_flowers_double_plant_sunflower_bottom.png": [45, 76, 40], "mcl_flowers_fern.png": [143, 132, 115], "flowers_tulip.png": [106, 84, 51], "mcl_flowers_double_plant_syringa_bottom.png": [63, 77, 60], "mcl_flowers_double_plant_fern_bottom.png": [140, 130, 113], "flowers_dandelion_yellow.png": [111, 111, 55], "mcl_flowers_double_plant_paeonia_bottom.png": [82, 83, 73], "mcl_flowers_double_plant_sunflower_back.png": [174, 146, 57], "mcl_flowers_allium.png": [120, 116, 144], "flowers_waterlily.png": [28, 81, 29], "mcl_flowers_tulip_pink.png": [100, 99, 90], "mcl_flowers_double_plant_sunflower_top.png": [48, 81, 44], "mcl_flowers_double_plant_syringa_top.png": [95, 90, 98], "mcl_flowers_double_plant_grass_bottom.png": [151, 140, 121], "mcl_flowers_double_plant_grass_inv.png": [48, 95, 43], "mcl_flowers_fern_inv.png": [43, 86, 39], "mcl_flowers_double_plant_fern_top.png": [148, 138, 119], "mcl_flowers_tallgrass_inv.png": [47, 92, 41], "mcl_flowers_double_plant_fern_inv.png": [45, 89, 40], "mcl_flowers_blue_orchid.png": [46, 91, 86], "mcl_armor_leggings_iron.png": [132, 128, 123], "mcl_armor_inv_leggings_iron.png": [130, 125, 120], "mcl_armor_chestplate_chain_preview.png": [124, 98, 90], "mcl_armor_inv_helmet_gold.png": [178, 134, 51], "mcl_armor_leggings_chain.png": [64, 66, 69], "mcl_armor_helmet_chain_preview.png": [154, 150, 143], "mcl_armor_chestplate_diamond_preview.png": [102, 140, 160], "mcl_armor_inv_boots_iron.png": [134, 129, 124], "mcl_armor_boots_gold_preview.png": [178, 133, 42], "mcl_armor_leggings_diamond_preview.png": [80, 118, 138], "mcl_armor_inv_chestplate_chain.png": [128, 105, 96], "mcl_armor_helmet_diamond_preview.png": [101, 134, 152], "mcl_armor_boots_leather_preview.png": [129, 119, 101], "mcl_armor_inv_chestplate_gold.png": [171, 128, 55], "mcl_armor_inv_helmet_diamond.png": [109, 130, 142], "mcl_armor_leggings_leather_preview.png": [141, 134, 114], "mcl_armor_boots_leather.png": [122, 111, 93], "mcl_armor_inv_chestplate_diamond.png": [106, 146, 168], "mcl_armor_helmet_diamond.png": [70, 85, 93], "mcl_armor_chestplate_iron_preview.png": [143, 134, 123], "mcl_armor_inv_chestplate_leather.png": [143, 136, 118], "mcl_armor_boots_diamond.png": [87, 132, 157], "mcl_armor_leggings_diamond.png": [78, 102, 115], "mcl_armor_leggings_gold_preview.png": [185, 156, 108], "mcl_armor_chestplate_gold.png": [157, 117, 55], "mcl_armor_inv_helmet_chain.png": [140, 137, 132], "mcl_armor_boots_chain_preview.png": [78, 78, 79], "mcl_armor_inv_leggings_chain.png": [81, 81, 82], "mcl_armor_inv_helmet_iron.png": [143, 138, 133], "mcl_armor_helmet_leather.png": [130, 121, 102], "mcl_armor_chestplate_diamond.png": [110, 157, 183], "mcl_armor_leggings_leather.png": [119, 108, 91], "mcl_armor_leggings_iron_preview.png": [127, 122, 117], "mcl_armor_inv_boots_gold.png": [187, 142, 46], "mcl_armor_chestplate_leather.png": [139, 132, 112], "mcl_armor_boots_iron.png": [118, 113, 109], "mcl_armor_elytra.png": [75, 121, 147], "mcl_armor_helmet_chain.png": [127, 124, 121], "mcl_armor_helmet_gold_preview.png": [181, 138, 54], "mcl_armor_boots_iron_preview.png": [118, 113, 108], "mcl_armor_helmet_iron.png": [153, 149, 144], "mcl_armor_inv_boots_leather.png": [130, 121, 103], "mcl_armor_leggings_chain_preview.png": [54, 56, 61], "mcl_armor_helmet_iron_preview.png": [143, 138, 132], "mcl_armor_helmet_leather_preview.png": [119, 109, 91], "mcl_armor_chestplate_leather_preview.png": [144, 138, 118], "mcl_armor_leggings_gold.png": [182, 158, 126], "mcl_armor_inv_leggings_gold.png": [175, 145, 97], "mcl_armor_chestplate_iron.png": [130, 120, 112], "mcl_armor_inv_elytra.png": [76, 122, 148], "mcl_armor_boots_chain.png": [88, 88, 88], "mcl_armor_helmet_gold.png": [178, 136, 56], "mcl_armor_inv_boots_diamond.png": [75, 121, 147], "mcl_armor_inv_chestplate_iron.png": [135, 125, 115], "mcl_armor_inv_leggings_diamond.png": [75, 93, 103], "mcl_armor_inv_leggings_leather.png": [126, 116, 98], "mcl_armor_inv_helmet_leather.png": [140, 132, 114], "mcl_armor_inv_boots_chain.png": [69, 69, 72], "mcl_armor_chestplate_gold_preview.png": [169, 127, 56], "mcl_armor_chestplate_chain.png": [119, 98, 93], "mcl_armor_boots_gold.png": [160, 118, 42], "mcl_armor_boots_diamond_preview.png": [89, 141, 169], "mcl_walls_cobble_wall_top.png": [120, 114, 112], "mcl_walls_cobble_mossy_wall_top.png": [53, 97, 61], "mcl_walls_cobble_wall_side.png": [109, 103, 101], "mcl_walls_cobble_mossy_wall_side.png": [86, 98, 83], "mcl_hoppers_item.png": [44, 44, 44], "mcl_hoppers_hopper_top.png": [43, 43, 43], "mcl_hoppers_hopper_outside.png": [44, 43, 43], "mcl_hoppers_hopper_inside.png": [50, 50, 50], "mcl_stairs_stone_slab_top.png": [127, 118, 114], "mcl_stairs_stone_slab_side.png": [127, 117, 113], "mcl_stairs_turntexture.png": [255, 0, 255], "mcl_brewing_bottle_bg.png": [204, 204, 204], "mcl_brewing_bubble_sprite.png": [167, 167, 167], "mcl_brewing_side.png": [175, 156, 160], "mcl_brewing_inventory.png": [168, 168, 168], "mcl_brewing_bubbles_active.png": [186, 186, 186], "mcl_brewing_fuel_bg.png": [200, 200, 200], "mcl_brewing_potion_bg.png": [204, 204, 204], "mcl_brewing_bubbles.png": [154, 154, 154], "mcl_brewing_top.png": [139, 130, 126], "mcl_brewing_base.png": [130, 122, 118], "mcl_brewing_burner.png": [183, 183, 183], "mcl_brewing_burner_active.png": [212, 161, 132], "xpanes_top_glass_cyan.png": [76, 127, 153], "xpanes_top_glass_brown.png": [102, 76, 51], "xpanes_top_glass_magenta.png": [178, 75, 215], "xpanes_top_glass_light_blue.png": [102, 153, 216], "xpanes_top_glass_blue.png": [51, 76, 178], "xpanes_top_glass_gray.png": [76, 76, 76], "xpanes_top_glass_silver.png": [153, 153, 153], "xpanes_top_iron.png": [155, 146, 146], "xpanes_top_glass_black.png": [25, 25, 25], "xpanes_top_glass_white.png": [255, 255, 255], "xpanes_top_glass_lime.png": [127, 204, 25], "xpanes_top_glass_orange.png": [216, 127, 51], "xpanes_top_glass_purple.png": [127, 63, 178], "xpanes_top_glass_red.png": [153, 51, 51], "xpanes_top_glass_natural.png": [222, 222, 239], "xpanes_top_glass_green.png": [102, 127, 51], "xpanes_top_glass_pink.png": [241, 126, 164], "xpanes_pane_iron.png": [160, 152, 152], "xpanes_top_glass_yellow.png": [229, 229, 51], "hardened_clay_stained_pink.png": [164, 79, 76], "mcl_colorblocks_glazed_terracotta_yellow.png": [232, 199, 99], "mcl_colorblocks_glazed_terracotta_orange.png": [170, 146, 81], "mcl_colorblocks_concrete_powder_lime.png": [125, 186, 42], "mcl_colorblocks_concrete_brown.png": [98, 60, 32], "mcl_colorblocks_concrete_magenta.png": [171, 49, 162], "mcl_colorblocks_glazed_terracotta_magenta.png": [210, 108, 215], "mcl_colorblocks_concrete_silver.png": [128, 129, 118], "mcl_colorblocks_glazed_terracotta_grey.png": [90, 90, 90], "mcl_colorblocks_concrete_powder_blue.png": [72, 75, 169], "mcl_colorblocks_concrete_yellow.png": [241, 177, 21], "mcl_colorblocks_concrete_red.png": [146, 34, 34], "mcl_colorblocks_glazed_terracotta_lime.png": [152, 211, 72], "mcl_colorblocks_concrete_black.png": [8, 10, 15], "mcl_colorblocks_glazed_terracotta_silver.png": [134, 151, 151], "hardened_clay_stained_white.png": [213, 197, 184], "mcl_colorblocks_glazed_terracotta_green.png": [111, 135, 50], "mcl_colorblocks_glazed_terracotta_blue.png": [34, 65, 117], "mcl_colorblocks_concrete_powder_red.png": [172, 57, 52], "mcl_colorblocks_concrete_powder_cyan.png": [38, 150, 159], "hardened_clay_stained_purple.png": [81, 71, 123], "hardened_clay_stained_brown.png": [96, 69, 61], "hardened_clay_stained_grey.png": [110, 92, 85], "mcl_colorblocks_concrete_lime.png": [96, 171, 25], "hardened_clay_stained_blue.png": [68, 91, 143], "mcl_colorblocks_concrete_powder_white.png": [224, 225, 225], "hardened_clay_stained_yellow.png": [177, 128, 51], "hardened_clay_stained_light_blue.png": [91, 128, 171], "hardened_clay.png": [143, 104, 87], "mcl_colorblocks_concrete_cyan.png": [21, 123, 140], "mcl_colorblocks_glazed_terracotta_brown.png": [108, 88, 64], "mcl_colorblocks_concrete_grey.png": [56, 59, 64], "mcl_colorblocks_concrete_powder_magenta.png": [196, 94, 189], "mcl_colorblocks_concrete_powder_black.png": [22, 26, 30], "mcl_colorblocks_concrete_pink.png": [213, 103, 144], "mcl_colorblocks_concrete_powder_orange.png": [227, 141, 38], "mcl_colorblocks_glazed_terracotta_cyan.png": [90, 131, 136], "mcl_colorblocks_glazed_terracotta_red.png": [184, 67, 53], "mcl_colorblocks_concrete_green.png": [75, 94, 37], "mcl_colorblocks_concrete_blue.png": [46, 48, 147], "mcl_colorblocks_glazed_terracotta_light_blue.png": [99, 162, 204], "hardened_clay_stained_orange.png": [156, 95, 69], "mcl_colorblocks_concrete_powder_silver.png": [160, 160, 155], "mcl_colorblocks_concrete_powder_pink.png": [224, 148, 176], "hardened_clay_stained_silver.png": [149, 129, 117], "hardened_clay_stained_red.png": [159, 81, 66], "hardened_clay_stained_magenta.png": [150, 80, 85], "mcl_colorblocks_glazed_terracotta_black.png": [38, 22, 22], "mcl_colorblocks_concrete_white.png": [208, 214, 215], "hardened_clay_stained_green.png": [74, 101, 63], "hardened_clay_stained_lime.png": [105, 134, 73], "mcl_colorblocks_concrete_powder_green.png": [104, 127, 45], "mcl_colorblocks_concrete_light_blue.png": [37, 140, 200], "mcl_colorblocks_concrete_powder_brown.png": [128, 86, 54], "mcl_colorblocks_concrete_purple.png": [103, 32, 159], "hardened_clay_stained_cyan.png": [71, 107, 123], "mcl_colorblocks_concrete_powder_purple.png": [138, 58, 180], "mcl_colorblocks_concrete_powder_yellow.png": [230, 198, 54], "mcl_colorblocks_concrete_powder_light_blue.png": [75, 181, 212], "mcl_colorblocks_glazed_terracotta_pink.png": [251, 138, 170], "mcl_colorblocks_glazed_terracotta_purple.png": [112, 49, 152], "mcl_colorblocks_concrete_orange.png": [226, 101, 1], "mcl_colorblocks_concrete_powder_grey.png": [91, 98, 103], "hardened_clay_stained_black.png": [69, 52, 46], "mcl_colorblocks_glazed_terracotta_white.png": [188, 211, 202], "fire_basic_flame_animated.png": [206, 98, 34], "mcl_burning_hud_flame_animated.png": [206, 98, 34], "mcl_fire_fire_charge.png": [95, 58, 41], "mcl_burning_entity_flame_animated.png": [206, 98, 34], "mcl_fire_flint_and_steel.png": [96, 95, 93], "fire_basic_flame.png": [207, 100, 36], "dye_red.png": [113, 74, 47], "dye_yellow.png": [123, 91, 49], "dye_violet.png": [107, 76, 57], "dye_dark_green.png": [99, 81, 47], "mcl_dye_blue.png": [58, 101, 173], "dye_cyan.png": [104, 89, 60], "mcl_dye_lime.png": [107, 91, 53], "dye_pink.png": [120, 81, 61], "mcl_dye_light_blue.png": [103, 88, 70], "dye_dark_grey.png": [108, 81, 52], "mcl_dye_white.png": [205, 193, 166], "dye_grey.png": [113, 86, 58], "dye_magenta.png": [111, 79, 59], "dye_orange.png": [122, 85, 48], "mcl_dye_brown.png": [104, 75, 56], "mcl_dye_black.png": [56, 56, 64], "default_river_water_flowing_animated.png": [38, 123, 130], "default_river_water_source_animated.png": [37, 120, 130], "3d_armor_stand_item.png": [134, 114, 98], "mob_spawner.png": [40, 40, 40], "mcl_nether_quartz_chiseled_side.png": [194, 186, 183], "mcl_nether_quartz_pillar_top.png": [195, 188, 185], "mcl_nether_nether_wart.png": [190, 79, 75], "mcl_nether_nether_wart_stage_1.png": [86, 54, 51], "mcl_nether_quartz_ore.png": [133, 64, 53], "mcl_nether_soul_sand.png": [90, 70, 51], "mcl_nether_nether_wart_block.png": [175, 76, 73], "mcl_nether_nether_wart_stage_0.png": [53, 41, 38], "mcl_nether_quartz_block_bottom.png": [198, 191, 187], "mcl_nether_quartz_block_top.png": [198, 190, 187], "mcl_nether_quartz.png": [152, 149, 147], "mcl_nether_quartz_pillar_side.png": [195, 188, 184], "mcl_nether_netherbrick.png": [58, 24, 20], "mcl_nether_glowstone.png": [202, 154, 96], "mcl_nether_netherrack.png": [130, 50, 39], "mcl_nether_red_nether_brick.png": [69, 17, 5], "mcl_nether_quartz_chiseled_top.png": [197, 189, 186], "mcl_nether_glowstone_dust.png": [209, 137, 67], "mcl_nether_nether_wart_stage_2.png": [106, 57, 53], "mcl_nether_quartz_block_side.png": [198, 190, 187], "mcl_nether_nether_brick.png": [49, 23, 24], "mcl_nether_magma.png": [85, 33, 27], "mcl_cauldrons_cauldron_inner.png": [24, 24, 24], "mcl_cauldrons_cauldron_top.png": [54, 54, 54], "mcl_cauldrons_cauldron_bottom.png": [50, 37, 38], "mcl_cauldrons_cauldron.png": [47, 47, 47], "mcl_cauldrons_cauldron_side.png": [43, 43, 43], "mcl_beds_bed_side_bottom_magenta.png": [127, 48, 89], "mcl_beds_bed_blue.png": [73, 78, 105], "mcl_beds_bed_side_top_r_black.png": [99, 86, 75], "mcl_beds_bed_side_bottom_r_magenta.png": [132, 46, 94], "mcl_beds_bed_side_top_brown.png": [98, 76, 59], "mcl_beds_bed_lime.png": [96, 135, 66], "mcl_beds_bed_side_top_green.png": [98, 76, 59], "mcl_beds_bed_light_blue.png": [100, 107, 142], "mcl_beds_bed_pink.png": [184, 105, 115], "mcl_beds_bed_side_bottom_black.png": [66, 56, 47], "mcl_beds_bed_top_bottom_green.png": [57, 110, 29], "mcl_beds_bed_side_top_blue.png": [98, 76, 59], "mcl_beds_bed_top_top_pink.png": [217, 138, 147], "mcl_beds_bed_side_bottom_light_blue.png": [90, 94, 129], "mcl_beds_bed_side_bottom_blue.png": [63, 65, 90], "mcl_beds_bed_top_top_red.png": [173, 90, 83], "mcl_beds_bed_side_top_grey.png": [98, 76, 59], "mcl_beds_bed_top_top_white.png": [198, 190, 183], "mcl_beds_bed_top_top_black.png": [107, 100, 92], "mcl_beds_bed_top_bottom_brown.png": [101, 69, 38], "mcl_beds_bed_top_bottom_pink.png": [232, 105, 135], "mcl_beds_bed_side_bottom_r_pink.png": [183, 95, 106], "mcl_beds_bed_side_bottom_r_green.png": [73, 97, 42], "mcl_beds_bed_side_bottom_r_grey.png": [86, 77, 69], "mcl_beds_bed_side_top_r_white.png": [158, 145, 134], "mcl_beds_bed_side_bottom_orange.png": [143, 84, 28], "mcl_beds_bed_side_bottom_purple.png": [105, 36, 112], "mcl_beds_bed_side_bottom_r_light_blue.png": [90, 97, 136], "mcl_beds_bed_side_top_r_magenta.png": [140, 81, 103], "mcl_beds_bed_side_bottom_r_yellow.png": [150, 131, 25], "mcl_beds_bed_side_top_r_pink.png": [176, 111, 113], "mcl_beds_bed_top_top_blue.png": [105, 112, 137], "mcl_beds_bed_side_bottom_green.png": [74, 94, 43], "mcl_beds_bed_side_bottom_r_blue.png": [61, 66, 95], "mcl_beds_bed_top_top_grey.png": [129, 121, 113], "mcl_beds_bed_black.png": [76, 68, 61], "mcl_beds_bed_top_top_silver.png": [159, 151, 143], "mcl_beds_bed_white.png": [173, 165, 158], "mcl_beds_bed_top_top_cyan.png": [105, 144, 135], "mcl_beds_bed_top_bottom_orange.png": [184, 91, 0], "mcl_beds_bed_side_top_silver.png": [98, 76, 59], "mcl_beds_bed_top_top_brown.png": [143, 118, 93], "mcl_beds_bed_side_top_r_light_blue.png": [115, 111, 132], "mcl_beds_bed_side_bottom_r_lime.png": [86, 129, 53], "mcl_beds_bed_red.png": [139, 58, 51], "mcl_beds_bed_top_bottom_lime.png": [79, 163, 47], "mcl_beds_bed_side_top_r_brown.png": [121, 97, 75], "mcl_beds_bed_side_bottom_r_silver.png": [119, 109, 102], "mcl_beds_bed_yellow.png": [154, 138, 41], "mcl_beds_bed_side_top_yellow.png": [98, 76, 59], "mcl_beds_bed_top_bottom_black.png": [37, 37, 37], "mcl_beds_bed_brown.png": [110, 85, 61], "mcl_beds_bed_side_top_orange.png": [98, 76, 59], "mcl_beds_bed_side_top_red.png": [98, 76, 59], "mcl_beds_bed_top_top_purple.png": [148, 79, 161], "mcl_beds_bed_side_bottom_pink.png": [177, 93, 102], "mcl_beds_bed_side_top_r_grey.png": [112, 99, 88], "mcl_beds_bed_side_top_r_blue.png": [97, 91, 104], "mcl_beds_bed_side_top_purple.png": [98, 76, 59], "mcl_beds_bed_side_top_cyan.png": [98, 76, 59], "mcl_beds_bed_top_bottom_blue.png": [32, 60, 119], "mcl_beds_bed_side_bottom_yellow.png": [143, 125, 28], "mcl_beds_bed_side_top_black.png": [98, 76, 59], "mcl_beds_bed_top_top_orange.png": [188, 130, 72], "mcl_beds_bed_top_bottom_silver.png": [129, 129, 129], "mcl_beds_bed_top_top_green.png": [117, 140, 88], "mcl_beds_bed_cyan.png": [73, 111, 103], "mcl_beds_bed_top_bottom_red.png": [157, 20, 20], "mcl_beds_bed_top_bottom_purple.png": [111, 0, 163], "mcl_beds_bed_side_top_r_silver.png": [133, 120, 109], "mcl_beds_bed_side_bottom_grey.png": [86, 76, 67], "mcl_beds_bed_grey.png": [96, 88, 81], "mcl_beds_bed_side_top_r_yellow.png": [151, 132, 62], "mcl_beds_bed_side_top_r_green.png": [103, 111, 72], "mcl_beds_bed_side_bottom_brown.png": [100, 73, 48], "mcl_beds_bed_magenta.png": [138, 60, 104], "mcl_beds_bed_side_bottom_r_red.png": [134, 44, 37], "mcl_beds_bed_side_bottom_r_brown.png": [101, 73, 47], "mcl_beds_bed_side_top_lime.png": [98, 76, 59], "mcl_beds_bed_side_top_light_blue.png": [98, 76, 59], "mcl_beds_bed_side_bottom_red.png": [129, 47, 38], "mcl_beds_bed_bottom_top.png": [48, 38, 29], "mcl_beds_bed_top_bottom_grey.png": [76, 76, 76], "mcl_beds_bed_side_bottom_r_orange.png": [150, 86, 25], "mcl_beds_bed_side_bottom_r_black.png": [64, 54, 47], "mcl_beds_bed_top_bottom_cyan.png": [32, 119, 114], "mcl_beds_bed_side_bottom_silver.png": [116, 106, 97], "mcl_beds_bed_side_top_magenta.png": [98, 76, 59], "mcl_beds_bed_top_bottom_white.png": [201, 201, 201], "mcl_beds_bed_side_top_r_orange.png": [151, 105, 62], "mcl_beds_bed_top_bottom_magenta.png": [154, 23, 118], "mcl_beds_bed_side_top_r_lime.png": [110, 131, 80], "mcl_beds_bed_top_top_magenta.png": [172, 92, 137], "mcl_beds_bed_bottom_bottom.png": [48, 38, 29], "mcl_beds_bed_side_top_r_purple.png": [125, 73, 119], "mcl_beds_bed_side_top_r_cyan.png": [97, 113, 103], "mcl_beds_bed_side_top_white.png": [98, 76, 59], "mcl_beds_bed_side_bottom_r_cyan.png": [61, 101, 93], "mcl_beds_bed_side_bottom_cyan.png": [63, 97, 89], "mcl_beds_bed_side_bottom_white.png": [161, 151, 142], "mcl_beds_bed_top_bottom_yellow.png": [184, 169, 0], "mcl_beds_bed_top_bottom_light_blue.png": [82, 113, 182], "mcl_beds_bed_top_top_lime.png": [130, 169, 98], "mcl_beds_bed_silver.png": [109, 100, 93], "mcl_beds_bed_purple.png": [115, 47, 128], "mcl_beds_bed_side_top_r_red.png": [141, 80, 69], "mcl_beds_bed_top_top_light_blue.png": [132, 141, 174], "mcl_beds_bed_side_bottom_r_purple.png": [107, 32, 120], "mcl_beds_bed_side_bottom_r_white.png": [161, 151, 144], "mcl_beds_bed_orange.png": [154, 96, 41], "mcl_beds_bed_top_bottom_gray.png": [57, 57, 57], "mcl_beds_bed_side_bottom_lime.png": [85, 122, 53], "mcl_beds_bed_green.png": [85, 107, 56], "mcl_beds_bed_top_top_yellow.png": [188, 172, 72], "mcl_beds_bed_side_top_pink.png": [98, 76, 59], "mcl_sponges_sponge_wet_river_water.png": [157, 141, 104], "mcl_sponges_sponge.png": [210, 177, 118], "mcl_sponges_sponge_wet.png": [156, 134, 92], "farming_mushroom_red.png": [169, 59, 58], "mcl_mushrooms_mushroom_block_inside.png": [218, 175, 136], "mcl_mushrooms_mushroom_block_skin_brown.png": [131, 86, 68], "mcl_mushrooms_mushroom_block_skin_stem.png": [204, 183, 149], "mcl_mushrooms_mushroom_block_skin_red.png": [137, 39, 25], "farming_mushroom_brown.png": [121, 81, 59], "farming_mushroom_stew.png": [134, 97, 67], "default_tool_goldsword.png": [194, 154, 70], "default_tool_steelsword.png": [134, 130, 125], "default_tool_woodsword.png": [100, 82, 68], "default_tool_goldshovel.png": [167, 133, 64], "default_tool_steelpick.png": [137, 128, 119], "default_tool_woodshovel.png": [108, 90, 76], "default_tool_goldpick.png": [172, 139, 73], "default_tool_woodaxe.png": [110, 92, 77], "default_tool_diamondsword.png": [105, 133, 149], "default_tool_steelshovel.png": [125, 115, 107], "default_tool_stonesword.png": [133, 125, 118], "default_tool_woodpick.png": [110, 91, 76], "default_tool_shears.png": [139, 132, 124], "default_tool_goldaxe.png": [160, 128, 66], "default_tool_stoneshovel.png": [126, 116, 107], "default_tool_diamondaxe.png": [103, 110, 113], "default_tool_diamondshovel.png": [106, 125, 134], "default_tool_steelaxe.png": [129, 119, 110], "default_tool_stoneaxe.png": [126, 115, 104], "default_tool_diamondpick.png": [92, 105, 111], "default_tool_stonepick.png": [126, 114, 104], "mcl_chests_ender_chest_right.png": [73, 67, 64], "mcl_chests_chest_trapped_right.png": [98, 78, 62], "default_chest_front.png": [85, 70, 58], "mcl_chests_blue_shulker_box_top.png": [67, 85, 119], "mcl_chests_chest_left.png": [99, 78, 63], "mcl_chests_dark_green_shulker_box_top.png": [67, 111, 70], "mcl_chests_chest_back.png": [92, 75, 61], "mcl_chests_ender_chest_bottom.png": [61, 55, 55], "mcl_chests_ender.png": [70, 62, 58], "mcl_chests_brown_shulker_box_top.png": [73, 63, 55], "mcl_chests_chest_trapped_back.png": [92, 75, 61], "mcl_chests_chest_trapped_side_big.png": [96, 77, 62], "mcl_chests_magenta_shulker_box_top.png": [128, 81, 124], "mcl_chests_ender_chest_back.png": [72, 66, 64], "mcl_chests_chest_trapped_bottom.png": [118, 91, 70], "mcl_chests_chest_trapped_front.png": [86, 68, 57], "default_chest_side_big.png": [96, 77, 62], "mcl_chests_green_shulker_box_top.png": [88, 122, 75], "mcl_chests_pink_shulker_box_top.png": [163, 116, 158], "mcl_chests_trapped.png": [95, 76, 61], "mcl_chests_blank.png": [255, 255, 255], "mcl_chests_normal_double.png": [98, 78, 62], "mcl_chests_chest_trapped_top.png": [88, 73, 61], "mcl_chests_normal.png": [95, 76, 61], "default_chest_front_big.png": [93, 75, 61], "mcl_chests_ender_chest_front.png": [76, 69, 65], "mcl_chests_white_shulker_box_top.png": [176, 178, 187], "mcl_chests_cyan_shulker_box_top.png": [67, 101, 121], "mcl_chests_chest_trapped_top_big.png": [100, 80, 65], "default_chest_top_big.png": [100, 80, 65], "mcl_chests_grey_shulker_box_top.png": [126, 129, 138], "mcl_chests_red_shulker_box_top.png": [132, 58, 57], "mcl_chests_trapped_double.png": [98, 78, 62], "mcl_chests_violet_shulker_box_top.png": [120, 71, 88], "mcl_chests_chest_trapped_front_big.png": [94, 75, 61], "mcl_chests_lightblue_shulker_box_top.png": [96, 130, 155], "mcl_chests_dark_grey_shulker_box_top.png": [87, 90, 99], "mcl_chests_black_shulker_box_top.png": [56, 57, 62], "mcl_chests_chest_right.png": [98, 78, 62], "mcl_chests_yellow_shulker_box_top.png": [165, 116, 53], "mcl_chests_chest_bottom.png": [118, 91, 70], "default_chest_top.png": [88, 73, 61], "mcl_chests_ender_chest_top.png": [70, 64, 61], "mcl_chests_ender_chest_left.png": [73, 67, 64], "mcl_chests_chest_trapped_left.png": [99, 78, 63], "mcl_chests_orange_shulker_box_top.png": [143, 74, 51], "screwdriver.png": [132, 119, 108], "_un.png": [0, 0, 0], "_at.png": [0, 0, 0], "_s_.png": [0, 0, 0], "_sz.png": [0, 0, 0], "_q.png": [0, 0, 0], "_1.png": [0, 0, 0], "_h_.png": [0, 0, 0], "_o_tilde.png": [0, 0, 0], "_q_.png": [0, 0, 0], "_ae.png": [0, 0, 0], "_e_circumflex_.png": [0, 0, 0], "_ex.png": [0, 0, 0], "_e_.png": [0, 0, 0], "_qo.png": [0, 0, 0], "_z_.png": [0, 0, 0], "_ps.png": [0, 0, 0], "_pound.png": [0, 0, 0], "_div.png": [0, 0, 0], "_l_.png": [0, 0, 0], "_pilcrow.png": [0, 0, 0], "_3_sup.png": [0, 0, 0], "_e_acute.png": [0, 0, 0], "_9.png": [0, 0, 0], "_e_grave_.png": [0, 0, 0], "_u_acute.png": [0, 0, 0], "_a_sup.png": [0, 0, 0], "_sr.png": [0, 0, 0], "_v.png": [0, 0, 0], "_ue_.png": [0, 0, 0], "_t_.png": [0, 0, 0], "_cl.png": [0, 0, 0], "_n_tilde_.png": [0, 0, 0], "_p_.png": [0, 0, 0], "_c.png": [0, 0, 0], "_a.png": [0, 0, 0], "_a_circumflex_.png": [0, 0, 0], "_8.png": [0, 0, 0], "_s.png": [0, 0, 0], "_o_.png": [0, 0, 0], "_1_4.png": [0, 0, 0], "_e_grave.png": [0, 0, 0], "_o_dash.png": [0, 0, 0], "_5.png": [0, 0, 0], "_d_dash_.png": [0, 0, 0], "_i_grave.png": [0, 0, 0], "_vb.png": [0, 0, 0], "_sp.png": [255, 255, 255], "_a_acute_.png": [0, 0, 0], "_as.png": [0, 0, 0], "_y_acute.png": [0, 0, 0], "_3_4.png": [0, 0, 0], "_6.png": [0, 0, 0], "_7.png": [0, 0, 0], "_tl.png": [0, 0, 0], "_t.png": [0, 0, 0], "_y.png": [0, 0, 0], "_ca.png": [0, 0, 0], "_e.png": [0, 0, 0], "_hs.png": [0, 0, 0], "_copyright.png": [0, 0, 0], "_l.png": [0, 0, 0], "_h.png": [0, 0, 0], "_u_circumflex_.png": [0, 0, 0], "_i_acute_.png": [0, 0, 0], "_ha.png": [0, 0, 0], "_y_diaresis.png": [0, 0, 0], "_gt.png": [0, 0, 0], "_b.png": [0, 0, 0], "_degree.png": [0, 0, 0], "_a_tilde_.png": [0, 0, 0], "_u_.png": [0, 0, 0], "_o_sup.png": [0, 0, 0], "_m_.png": [0, 0, 0], "_c_.png": [0, 0, 0], "_cr.png": [0, 0, 0], "_3.png": [0, 0, 0], "_currency.png": [0, 0, 0], "_f.png": [0, 0, 0], "_cedille.png": [0, 0, 0], "_u_grave_.png": [0, 0, 0], "_dt.png": [0, 0, 0], "_am.png": [0, 0, 0], "_c_cedille_.png": [0, 0, 0], "_u_acute_.png": [0, 0, 0], "_bl.png": [0, 0, 0], "_registered.png": [0, 0, 0], "_i_acute.png": [0, 0, 0], "_lt.png": [0, 0, 0], "_e_acute_.png": [0, 0, 0], "_paragraph.png": [0, 0, 0], "_i_grave_.png": [0, 0, 0], "_o.png": [0, 0, 0], "_1_sup.png": [0, 0, 0], "mcl_signs_sign.png": [114, 89, 69], "_yen.png": [0, 0, 0], "_b_.png": [0, 0, 0], "_macron.png": [0, 0, 0], "_qu_inv.png": [0, 0, 0], "_o_dash_.png": [0, 0, 0], "_guill_right.png": [0, 0, 0], "_p.png": [0, 0, 0], "_thorn_.png": [0, 0, 0], "_2_sup.png": [0, 0, 0], "_pr.png": [0, 0, 0], "default_sign.png": [145, 115, 88], "_times_dot.png": [0, 0, 0], "_acute.png": [0, 0, 0], "_g_.png": [0, 0, 0], "_o_acute_.png": [0, 0, 0], "_a_tilde.png": [0, 0, 0], "_j.png": [0, 0, 0], "_k.png": [0, 0, 0], "_co.png": [0, 0, 0], "_dv.png": [0, 0, 0], "_o_circumflex.png": [0, 0, 0], "_a_ring.png": [0, 0, 0], "_br.png": [0, 0, 0], "_d.png": [0, 0, 0], "_ap.png": [0, 0, 0], "_sl.png": [0, 0, 0], "_mn.png": [0, 0, 0], "_m.png": [0, 0, 0], "_ae_lig.png": [0, 0, 0], "_thorn.png": [0, 0, 0], "_2.png": [0, 0, 0], "_gr.png": [0, 0, 0], "_i.png": [0, 0, 0], "_y_acute_.png": [0, 0, 0], "_diaresis.png": [0, 0, 0], "_oe.png": [0, 0, 0], "_mu.png": [0, 0, 0], "_guill_left.png": [0, 0, 0], "_times_cross.png": [0, 0, 0], "_ae_.png": [0, 0, 0], "_w.png": [0, 0, 0], "_u.png": [0, 0, 0], "_broken_bar.png": [0, 0, 0], "_4.png": [0, 0, 0], "_plus_minus.png": [0, 0, 0], "_1_2.png": [0, 0, 0], "_u_circumflex.png": [0, 0, 0], "_w_.png": [0, 0, 0], "_x_.png": [0, 0, 0], "_e_circumflex.png": [0, 0, 0], "_g.png": [0, 0, 0], "_o_tilde_.png": [0, 0, 0], "_ae_lig_.png": [0, 0, 0], "_v_.png": [0, 0, 0], "_dl.png": [0, 0, 0], "_a_grave.png": [0, 0, 0], "_re.png": [0, 0, 0], "_a_acute.png": [0, 0, 0], "_qu.png": [0, 0, 0], "_oe_.png": [0, 0, 0], "_n_tilde.png": [0, 0, 0], "_eq.png": [0, 0, 0], "_d_.png": [0, 0, 0], "_sm.png": [0, 0, 0], "_y_.png": [0, 0, 0], "_not.png": [0, 0, 0], "_n.png": [0, 0, 0], "_j_.png": [0, 0, 0], "_k_.png": [0, 0, 0], "_0.png": [0, 0, 0], "_o_grave_.png": [0, 0, 0], "_r_.png": [0, 0, 0], "_r.png": [0, 0, 0], "_u_grave.png": [0, 0, 0], "_ee_.png": [0, 0, 0], "_c_cedille.png": [0, 0, 0], "_ex_inv.png": [0, 0, 0], "_cm.png": [0, 0, 0], "_o_grave.png": [0, 0, 0], "_x.png": [0, 0, 0], "_i_.png": [0, 0, 0], "_n_.png": [0, 0, 0], "_rc.png": [0, 0, 0], "_a_.png": [0, 0, 0], "_a_grave_.png": [0, 0, 0], "_ee.png": [0, 0, 0], "_o_acute.png": [0, 0, 0], "_a_ring_.png": [0, 0, 0], "_i_circumflex_.png": [0, 0, 0], "_cent.png": [0, 0, 0], "_d_dash.png": [0, 0, 0], "_f_.png": [0, 0, 0], "_o_circumflex_.png": [0, 0, 0], "_ue.png": [0, 0, 0], "_a_circumflex.png": [0, 0, 0], "_i_circumflex.png": [0, 0, 0], "_z.png": [0, 0, 0], "gui_furnace_arrow_fg.png": [239, 239, 239], "default_furnace_front.png": [105, 95, 91], "default_furnace_fire_bg.png": [139, 139, 139], "default_furnace_top.png": [148, 138, 133], "default_furnace_fire_fg.png": [179, 115, 70], "default_furnace_side.png": [117, 107, 102], "gui_furnace_arrow_bg.png": [139, 139, 139], "default_furnace_front_active.png": [119, 95, 85], "default_furnace_bottom.png": [148, 138, 133], "default_torch_on_floor.png": [115, 82, 59], "default_torch_on_floor_animated.png": [116, 84, 61], "default_tnt_bottom.png": [161, 54, 58], "mcl_tnt_blink.png": [255, 255, 255], "default_tnt_top.png": [125, 54, 57], "default_tnt_side.png": [178, 105, 98], "mcl_heads_skeleton.png": [125, 125, 125], "mcl_heads_skeleton_node.png": [124, 124, 124], "mcl_heads_creeper_node.png": [98, 107, 71], "mcl_heads_zombie.png": [66, 104, 69], "mcl_heads_creeper.png": [92, 110, 68], "mcl_heads_steve_node.png": [115, 70, 58], "mcl_heads_skeleton_preview.png": [128, 127, 127], "mcl_heads_steve_preview.png": [117, 83, 66], "mcl_heads_zombie_node.png": [78, 110, 105], "mcl_heads_steve.png": [108, 76, 59], "mcl_heads_wither_skeleton_node.png": [50, 50, 50], "mcl_heads_zombie_preview.png": [66, 103, 68], "mcl_heads_creeper_preview.png": [88, 110, 65], "mcl_heads_wither_skeleton.png": [50, 50, 50], "mcl_heads_wither_skeleton_preview.png": [50, 50, 50], "mcl_flowerpots_cactus.png": [109, 83, 52], "mcl_flowerpots_flowerpot_inventory.png": [121, 54, 45], "mcl_flowerpots_flowerpot.png": [120, 55, 47], "bucket_lava.png": [166, 127, 113], "bucket_river_water.png": [139, 152, 155], "bucket_water.png": [139, 147, 155], "bucket.png": [147, 143, 139], "mcl_anvils_anvil_top_damaged_1.png": [48, 48, 48], "mcl_anvils_anvil_top_damaged_2.png": [46, 46, 46], "mcl_anvils_anvil_top_damaged_0.png": [50, 50, 50], "mcl_anvils_anvil_side.png": [45, 45, 45], "mcl_anvils_inventory.png": [157, 157, 157], "mcl_anvils_anvil_base.png": [40, 40, 40], "mcl_maps_map_filled.png": [213, 176, 148], "mcl_maps_map_empty.png": [217, 187, 157], "mcl_maps_map_filled_markings.png": [183, 183, 183], "mcl_dispensers_dispenser_front_vertical.png": [115, 104, 99], "mcl_dispensers_dispenser_front_horizontal.png": [105, 96, 92], "jeija_wall_lever.png": [95, 80, 69], "mesecons_delayer_front_locked_off.png": [97, 85, 77], "mesecons_delayer_locked_on.png": [114, 100, 95], "mesecons_delayer_sides_locked_off.png": [95, 80, 73], "mesecons_delayer_sides_on.png": [106, 71, 63], "mesecons_delayer_item.png": [100, 87, 82], "mesecons_delayer_end_locked_off.png": [97, 85, 77], "mesecons_delayer_end_locked_on.png": [101, 85, 78], "mesecons_delayer_ends_off.png": [99, 86, 80], "mesecons_delayer_front_locked_on.png": [101, 85, 77], "mesecons_delayer_ends_on.png": [105, 87, 81], "mesecons_delayer_sides_locked_on.png": [104, 81, 74], "mesecons_delayer_locked_off.png": [110, 99, 95], "mesecons_delayer_sides_off.png": [90, 69, 61], "mesecons_delayer_off.png": [112, 100, 96], "mesecons_delayer_on.png": [116, 101, 97], "redstone_redstone_dust_line0.png": [168, 168, 168], "redstone_redstone_dust.png": [81, 0, 0], "redstone_redstone_dust_dot.png": [168, 168, 168], "redstone_redstone_dust_line1.png": [173, 173, 173], "jeija_commandblock_off.png": [110, 99, 96], "jeija_commandblock_on.png": [110, 99, 96], "redstone_redstone_block.png": [128, 8, 9], "jeija_torches_on.png": [102, 68, 56], "jeija_torches_off.png": [90, 66, 54], "mesecons_button_wield_mask.png": [255, 126, 126], "mcl_droppers_dropper_front_vertical.png": [118, 108, 103], "mcl_droppers_dropper_front_horizontal.png": [110, 101, 96], "mesecons_noteblock.png": [104, 81, 63], "jeija_solar_panel_inverted.png": [100, 107, 117], "jeija_solar_panel.png": [124, 113, 101], "jeija_solar_panel_side.png": [60, 47, 36], "mcl_observers_observer_top.png": [139, 128, 123], "mcl_observers_observer_front.png": [95, 80, 84], "mcl_observers_observer_back_lit.png": [75, 67, 65], "mcl_observers_observer_back.png": [72, 67, 64], "mcl_observers_observer_side.png": [111, 103, 99], "mesecons_piston_pusher_front_sticky.png": [97, 81, 63], "mesecons_piston_pusher_top.png": [106, 83, 65], "mesecons_piston_back.png": [110, 101, 98], "mesecons_piston_on_front.png": [111, 101, 98], "mesecons_piston_pusher_back.png": [106, 83, 65], "mesecons_piston_bottom.png": [120, 107, 100], "mesecons_piston_pusher_right.png": [106, 83, 65], "mesecons_piston_pusher_bottom.png": [106, 83, 65], "mesecons_piston_pusher_front.png": [106, 83, 65], "mesecons_piston_pusher_left.png": [106, 83, 65], "jeija_lightstone_gray_on.png": [97, 56, 37], "jeija_lightstone_gray_off.png": [64, 49, 43], "mcl_comparators_sides_on.png": [105, 87, 81], "mcl_comparators_comp.png": [61, 20, 20], "mcl_comparators_on.png": [116, 102, 98], "mcl_comparators_sides_comp.png": [99, 88, 83], "mcl_comparators_off.png": [113, 102, 98], "mcl_comparators_ends_comp.png": [99, 88, 83], "mcl_comparators_ends_sub.png": [105, 88, 83], "mcl_comparators_ends_off.png": [96, 80, 74], "mcl_comparators_ends_on.png": [105, 81, 75], "mcl_comparators_sub.png": [112, 25, 25], "mcl_comparators_item.png": [98, 83, 79], "mcl_comparators_sides_off.png": [99, 86, 80], "mcl_comparators_sides_sub.png": [105, 88, 83], "default_book.png": [103, 67, 44], "default_bookshelf.png": [84, 67, 54], "mcl_books_book_written.png": [110, 74, 44], "mcl_books_book_bg.png": [203, 180, 151], "mcl_books_button9_pressed.png": [145, 112, 86], "mcl_books_button9.png": [145, 112, 86], "mcl_books_book_writable.png": [151, 122, 108], "mcl_books_bookshelf_top.png": [109, 84, 65], "wool_dark_grey.png": [96, 87, 87], "wool_grey.png": [143, 134, 134], "wool_magenta.png": [140, 85, 125], "wool_black.png": [45, 42, 42], "wool_orange.png": [188, 106, 45], "wool_blue.png": [43, 73, 125], "wool_yellow.png": [201, 163, 69], "wool_pink.png": [171, 91, 108], "wool_dark_green.png": [53, 91, 51], "wool_brown.png": [86, 57, 43], "wool_red.png": [132, 42, 45], "mcl_wool_light_blue.png": [91, 130, 180], "wool_cyan.png": [30, 94, 113], "mcl_wool_lime.png": [107, 151, 76], "wool_white.png": [212, 199, 182], "wool_violet.png": [77, 57, 102], "mcl_potions_melon_speckled.png": [170, 97, 62], "mcl_potions_effect_swift.png": [106, 96, 85], "mcl_potions_spider_eye_fermented.png": [143, 97, 62], "mcl_potions_splash_bottle.png": [168, 156, 183], "mcl_potions_effect_water_breathing.png": [59, 69, 100], "mcl_potions_effect_leaping.png": [100, 91, 86], "mcl_potions_effect_weak.png": [127, 126, 126], "mcl_potions_dragon_breath.png": [171, 137, 163], "mcl_potions_effect_food_poisoning.png": [112, 123, 89], "hudbars_icon_regenerate.png": [195, 77, 114], "mcl_potions_effect_fire_proof.png": [112, 68, 68], "mcl_potions_splash_overlay.png": [202, 202, 202], "mcl_potions_effect_invisible.png": [96, 103, 95], "hbhunger_icon_regen_poison.png": [147, 111, 115], "mcl_potions_effect_slow.png": [78, 81, 85], "mcl_potions_lingering_bottle.png": [181, 159, 192], "mcl_potions_potion_overlay.png": [201, 201, 201], "mcl_potions_effect_regenerating.png": [133, 90, 83], "mcl_potions_arrow_inv.png": [171, 165, 160], "mcl_potions_effect_night_vision.png": [86, 99, 74], "mcl_potions_potion_bottle.png": [156, 172, 203], "mcl_potions_effect_poisoned.png": [78, 110, 80], "mcl_potions_effect_strong.png": [100, 82, 97], "crafting_workbench_front.png": [120, 93, 72], "gui_crafting_arrow.png": [139, 139, 139], "crafting_workbench_side.png": [120, 93, 72], "crafting_workbench_top.png": [152, 121, 93], "mcl_enchanting_glyph_11.png": [209, 209, 231], "mcl_enchanting_glyph_14.png": [209, 209, 231], "mcl_enchanting_glyph_6.png": [209, 209, 231], "mcl_enchanting_glyph_8.png": [209, 209, 231], "mcl_enchanting_glyph_9.png": [209, 209, 231], "mcl_enchanting_glyph_3.png": [209, 209, 231], "mcl_enchanting_number_1_off.png": [255, 255, 255], "mcl_enchanting_number_3_off.png": [255, 255, 255], "mcl_enchanting_number_3.png": [151, 47, 40], "mcl_enchanting_book_open.png": [153, 123, 99], "mcl_enchanting_button_off.png": [255, 255, 255], "mcl_enchanting_glyph_2.png": [209, 209, 231], "mcl_enchanting_glyph_1.png": [209, 209, 231], "mcl_enchanting_button.png": [255, 255, 255], "mcl_enchanting_table_side.png": [66, 58, 55], "mcl_enchanting_book_closed.png": [112, 78, 55], "mcl_enchanting_table_bottom.png": [58, 51, 52], "mcl_enchanting_glyph_15.png": [209, 209, 231], "mcl_enchanting_number_2_off.png": [255, 255, 255], "mcl_enchanting_glyph_5.png": [209, 209, 231], "mcl_enchanting_number_1.png": [149, 45, 39], "mcl_enchanting_glyph_7.png": [209, 209, 231], "mcl_enchanting_table_top.png": [88, 86, 84], "mcl_enchanting_number_2.png": [149, 46, 39], "mcl_enchanting_glyph_16.png": [209, 209, 231], "mcl_enchanting_button_hovered.png": [255, 255, 255], "mcl_enchanting_book_enchanted.png": [122, 69, 46], "mcl_enchanting_glyph_4.png": [209, 209, 231], "mcl_enchanting_glyph_10.png": [209, 209, 231], "mcl_enchanting_glyph_13.png": [209, 209, 231], "mcl_enchanting_glyph_17.png": [209, 209, 231], "mcl_enchanting_glyph_18.png": [209, 209, 231], "mcl_enchanting_lapis_background.png": [255, 255, 255], "mcl_enchanting_button_background.png": [229, 202, 171], "mcl_enchanting_glyph_12.png": [209, 209, 231], "doc_basics_gameplay_mtg_2.png": [151, 168, 207], "doc_basics_liquids_renewable_1.png": [139, 146, 159], "doc_basics_players_sam.png": [95, 133, 106], "doc_basics_players_flat.png": [127, 155, 130], "doc_basics_craft_shapeless_2.png": [52, 52, 48], "doc_basics_build.png": [84, 84, 55], "doc_basics_pointing.png": [66, 104, 32], "doc_basics_nodes.png": [108, 104, 94], "doc_basics_craft_groups_2.png": [65, 58, 52], "doc_basics_craft_groups_1.png": [57, 57, 58], "doc_basics_inventory.png": [47, 47, 45], "doc_basics_minimap_radar.png": [73, 164, 128], "doc_basics_sneak.png": [70, 69, 69], "doc_basics_camera_behind.png": [108, 144, 135], "doc_basics_craft_repair.png": [47, 46, 45], "doc_basics_hotbar_relations.png": [85, 84, 69], "doc_basics_gameplay_lott.png": [119, 122, 112], "doc_basics_tools_mining.png": [64, 62, 59], "doc_basics_players_lott.png": [180, 193, 224], "doc_basics_gameplay_outback.png": [146, 114, 109], "doc_basics_gameplay_pixture.png": [94, 120, 57], "doc_basics_craft_grid.png": [46, 46, 46], "doc_basics_craft_groups_3.png": [61, 58, 55], "doc_basics_camera_front.png": [99, 133, 110], "doc_basics_minimap_map.png": [149, 169, 183], "doc_basics_gameplay_mtg_1.png": [136, 117, 86], "doc_basics_gameplay_xtraores_xtension.png": [95, 15, 86], "doc_basics_light_torch.png": [25, 43, 14], "doc_basics_minimap_round.png": [160, 175, 189], "doc_basics_light_test.png": [133, 113, 69], "doc_basics_liquids_nonrenewable.png": [64, 87, 87], "doc_basics_gameplay_hades.png": [81, 70, 62], "doc_basics_gameplay_moontest.png": [75, 74, 79], "doc_basics_liquids_range.png": [146, 166, 179], "doc_basics_inventory_detail.png": [43, 41, 39], "doc_basics_camera_ego.png": [111, 147, 139], "doc_basics_tools.png": [46, 45, 42], "doc_basics_liquids_renewable_2.png": [136, 148, 166], "doc_basics_items_dropped.png": [195, 185, 147], "doc_basics_liquids_types.png": [146, 164, 171], "doc_basics_gameplay_carbone_ng.png": [121, 118, 89], "doc_basics_craft_shaped.png": [55, 52, 50], "doc_basics_hotbar.png": [141, 175, 226], "doc_basics_craft_shapeless_1.png": [52, 52, 48], "doc_button_icon_lores.png": [19, 143, 183], "doc_awards_icon_generic.png": [14, 125, 162], "inventory_plus_doc_inventory_plus.png": [19, 143, 183], "doc_button_icon_hires.png": [30, 149, 188], "doc_identifier_identifier.png": [172, 151, 139], "doc_identifier_identifier_liquid.png": [125, 147, 190], "craftguide_clear_icon.png": [254, 254, 254], "craftguide_book.png": [84, 117, 39], "mcl_craftguide_fuel.png": [187, 121, 75], "craftguide_prev_icon.png": [255, 255, 255], "craftguide_zoomout_icon.png": [255, 255, 255], "craftguide_search_icon.png": [254, 254, 254], "craftguide_arrow.png": [139, 139, 139], "craftguide_zoomin_icon.png": [255, 255, 255], "craftguide_shapeless.png": [130, 130, 130], "craftguide_next_icon.png": [255, 255, 255]}